{"variants":[{"traits":[{"interfaceLanguage":"swift"}],"paths":["\/documentation\/spooktacularkit\/virtualmachinestate\/equatable-implementations"]}],"identifier":{"url":"doc:\/\/SpooktacularKit\/documentation\/SpooktacularKit\/VirtualMachineState\/Equatable-Implementations","interfaceLanguage":"swift"},"kind":"article","hierarchy":{"paths":[["doc:\/\/SpooktacularKit\/documentation\/SpooktacularKit","doc:\/\/SpooktacularKit\/documentation\/SpooktacularKit\/VirtualMachineState"],["doc:\/\/SpooktacularKit\/documentation\/SpooktacularKit","doc:\/\/SpooktacularKit\/documentation\/SpooktacularKit\/EC2MacDeployment","doc:\/\/SpooktacularKit\/documentation\/SpooktacularKit\/VirtualMachineState"],["doc:\/\/SpooktacularKit\/documentation\/SpooktacularKit","doc:\/\/SpooktacularKit\/documentation\/SpooktacularKit\/GitHubActionsGuide","doc:\/\/SpooktacularKit\/documentation\/SpooktacularKit\/VirtualMachineState"],["doc:\/\/SpooktacularKit\/documentation\/SpooktacularKit","doc:\/\/SpooktacularKit\/documentation\/SpooktacularKit\/CLIReference","doc:\/\/SpooktacularKit\/documentation\/SpooktacularKit\/EC2MacDeployment","doc:\/\/SpooktacularKit\/documentation\/SpooktacularKit\/VirtualMachineState"],["doc:\/\/SpooktacularKit\/documentation\/SpooktacularKit","doc:\/\/SpooktacularKit\/documentation\/SpooktacularKit\/CLIReference","doc:\/\/SpooktacularKit\/documentation\/SpooktacularKit\/GitHubActionsGuide","doc:\/\/SpooktacularKit\/documentation\/SpooktacularKit\/VirtualMachineState"],["doc:\/\/SpooktacularKit\/documentation\/SpooktacularKit","doc:\/\/SpooktacularKit\/documentation\/SpooktacularKit\/EC2MacDeployment","doc:\/\/SpooktacularKit\/documentation\/SpooktacularKit\/GitHubActionsGuide","doc:\/\/SpooktacularKit\/documentation\/SpooktacularKit\/VirtualMachineState"],["doc:\/\/SpooktacularKit\/documentation\/SpooktacularKit","doc:\/\/SpooktacularKit\/documentation\/SpooktacularKit\/GettingStarted","doc:\/\/SpooktacularKit\/documentation\/SpooktacularKit\/EC2MacDeployment","doc:\/\/SpooktacularKit\/documentation\/SpooktacularKit\/VirtualMachineState"],["doc:\/\/SpooktacularKit\/documentation\/SpooktacularKit","doc:\/\/SpooktacularKit\/documentation\/SpooktacularKit\/GettingStarted","doc:\/\/SpooktacularKit\/documentation\/SpooktacularKit\/GitHubActionsGuide","doc:\/\/SpooktacularKit\/documentation\/SpooktacularKit\/VirtualMachineState"],["doc:\/\/SpooktacularKit\/documentation\/SpooktacularKit","doc:\/\/SpooktacularKit\/documentation\/SpooktacularKit\/KubernetesGuide","doc:\/\/SpooktacularKit\/documentation\/SpooktacularKit\/GitHubActionsGuide","doc:\/\/SpooktacularKit\/documentation\/SpooktacularKit\/VirtualMachineState"],["doc:\/\/SpooktacularKit\/documentation\/SpooktacularKit","doc:\/\/SpooktacularKit\/documentation\/SpooktacularKit\/RemoteDesktop","doc:\/\/SpooktacularKit\/documentation\/SpooktacularKit\/EC2MacDeployment","doc:\/\/SpooktacularKit\/documentation\/SpooktacularKit\/VirtualMachineState"],["doc:\/\/SpooktacularKit\/documentation\/SpooktacularKit","doc:\/\/SpooktacularKit\/documentation\/SpooktacularKit\/Versioning","doc:\/\/SpooktacularKit\/documentation\/SpooktacularKit\/EC2MacDeployment","doc:\/\/SpooktacularKit\/documentation\/SpooktacularKit\/VirtualMachineState"],["doc:\/\/SpooktacularKit\/documentation\/SpooktacularKit","doc:\/\/SpooktacularKit\/documentation\/SpooktacularKit\/BlueBubblesGuide","doc:\/\/SpooktacularKit\/documentation\/SpooktacularKit\/GettingStarted","doc:\/\/SpooktacularKit\/documentation\/SpooktacularKit\/EC2MacDeployment","doc:\/\/SpooktacularKit\/documentation\/SpooktacularKit\/VirtualMachineState"],["doc:\/\/SpooktacularKit\/documentation\/SpooktacularKit","doc:\/\/SpooktacularKit\/documentation\/SpooktacularKit\/BlueBubblesGuide","doc:\/\/SpooktacularKit\/documentation\/SpooktacularKit\/GettingStarted","doc:\/\/SpooktacularKit\/documentation\/SpooktacularKit\/GitHubActionsGuide","doc:\/\/SpooktacularKit\/documentation\/SpooktacularKit\/VirtualMachineState"],["doc:\/\/SpooktacularKit\/documentation\/SpooktacularKit","doc:\/\/SpooktacularKit\/documentation\/SpooktacularKit\/BlueBubblesGuide","doc:\/\/SpooktacularKit\/documentation\/SpooktacularKit\/RemoteDesktop","doc:\/\/SpooktacularKit\/documentation\/SpooktacularKit\/EC2MacDeployment","doc:\/\/SpooktacularKit\/documentation\/SpooktacularKit\/VirtualMachineState"],["doc:\/\/SpooktacularKit\/documentation\/SpooktacularKit","doc:\/\/SpooktacularKit\/documentation\/SpooktacularKit\/CLIReference","doc:\/\/SpooktacularKit\/documentation\/SpooktacularKit\/EC2MacDeployment","doc:\/\/SpooktacularKit\/documentation\/SpooktacularKit\/GitHubActionsGuide","doc:\/\/SpooktacularKit\/documentation\/SpooktacularKit\/VirtualMachineState"],["doc:\/\/SpooktacularKit\/documentation\/SpooktacularKit","doc:\/\/SpooktacularKit\/documentation\/SpooktacularKit\/EC2MacDeployment","doc:\/\/SpooktacularKit\/documentation\/SpooktacularKit\/KubernetesGuide","doc:\/\/SpooktacularKit\/documentation\/SpooktacularKit\/GitHubActionsGuide","doc:\/\/SpooktacularKit\/documentation\/SpooktacularKit\/VirtualMachineState"],["doc:\/\/SpooktacularKit\/documentation\/SpooktacularKit","doc:\/\/SpooktacularKit\/documentation\/SpooktacularKit\/GettingStarted","doc:\/\/SpooktacularKit\/documentation\/SpooktacularKit\/CLIReference","doc:\/\/SpooktacularKit\/documentation\/SpooktacularKit\/EC2MacDeployment","doc:\/\/SpooktacularKit\/documentation\/SpooktacularKit\/VirtualMachineState"],["doc:\/\/SpooktacularKit\/documentation\/SpooktacularKit","doc:\/\/SpooktacularKit\/documentation\/SpooktacularKit\/GettingStarted","doc:\/\/SpooktacularKit\/documentation\/SpooktacularKit\/CLIReference","doc:\/\/SpooktacularKit\/documentation\/SpooktacularKit\/GitHubActionsGuide","doc:\/\/SpooktacularKit\/documentation\/SpooktacularKit\/VirtualMachineState"],["doc:\/\/SpooktacularKit\/documentation\/SpooktacularKit","doc:\/\/SpooktacularKit\/documentation\/SpooktacularKit\/GettingStarted","doc:\/\/SpooktacularKit\/documentation\/SpooktacularKit\/EC2MacDeployment","doc:\/\/SpooktacularKit\/documentation\/SpooktacularKit\/GitHubActionsGuide","doc:\/\/SpooktacularKit\/documentation\/SpooktacularKit\/VirtualMachineState"],["doc:\/\/SpooktacularKit\/documentation\/SpooktacularKit","doc:\/\/SpooktacularKit\/documentation\/SpooktacularKit\/GettingStarted","doc:\/\/SpooktacularKit\/documentation\/SpooktacularKit\/KubernetesGuide","doc:\/\/SpooktacularKit\/documentation\/SpooktacularKit\/GitHubActionsGuide","doc:\/\/SpooktacularKit\/documentation\/SpooktacularKit\/VirtualMachineState"],["doc:\/\/SpooktacularKit\/documentation\/SpooktacularKit","doc:\/\/SpooktacularKit\/documentation\/SpooktacularKit\/MLWorkloads","doc:\/\/SpooktacularKit\/documentation\/SpooktacularKit\/GettingStarted","doc:\/\/SpooktacularKit\/documentation\/SpooktacularKit\/EC2MacDeployment","doc:\/\/SpooktacularKit\/documentation\/SpooktacularKit\/VirtualMachineState"],["doc:\/\/SpooktacularKit\/documentation\/SpooktacularKit","doc:\/\/SpooktacularKit\/documentation\/SpooktacularKit\/MLWorkloads","doc:\/\/SpooktacularKit\/documentation\/SpooktacularKit\/GettingStarted","doc:\/\/SpooktacularKit\/documentation\/SpooktacularKit\/GitHubActionsGuide","doc:\/\/SpooktacularKit\/documentation\/SpooktacularKit\/VirtualMachineState"],["doc:\/\/SpooktacularKit\/documentation\/SpooktacularKit","doc:\/\/SpooktacularKit\/documentation\/SpooktacularKit\/MLWorkloads","doc:\/\/SpooktacularKit\/documentation\/SpooktacularKit\/KubernetesGuide","doc:\/\/SpooktacularKit\/documentation\/SpooktacularKit\/GitHubActionsGuide","doc:\/\/SpooktacularKit\/documentation\/SpooktacularKit\/VirtualMachineState"],["doc:\/\/SpooktacularKit\/documentation\/SpooktacularKit","doc:\/\/SpooktacularKit\/documentation\/SpooktacularKit\/MLWorkloads","doc:\/\/SpooktacularKit\/documentation\/SpooktacularKit\/RemoteDesktop","doc:\/\/SpooktacularKit\/documentation\/SpooktacularKit\/EC2MacDeployment","doc:\/\/SpooktacularKit\/documentation\/SpooktacularKit\/VirtualMachineState"],["doc:\/\/SpooktacularKit\/documentation\/SpooktacularKit","doc:\/\/SpooktacularKit\/documentation\/SpooktacularKit\/RemoteDesktop","doc:\/\/SpooktacularKit\/documentation\/SpooktacularKit\/CLIReference","doc:\/\/SpooktacularKit\/documentation\/SpooktacularKit\/EC2MacDeployment","doc:\/\/SpooktacularKit\/documentation\/SpooktacularKit\/VirtualMachineState"],["doc:\/\/SpooktacularKit\/documentation\/SpooktacularKit","doc:\/\/SpooktacularKit\/documentation\/SpooktacularKit\/RemoteDesktop","doc:\/\/SpooktacularKit\/documentation\/SpooktacularKit\/CLIReference","doc:\/\/SpooktacularKit\/documentation\/SpooktacularKit\/GitHubActionsGuide","doc:\/\/SpooktacularKit\/documentation\/SpooktacularKit\/VirtualMachineState"],["doc:\/\/SpooktacularKit\/documentation\/SpooktacularKit","doc:\/\/SpooktacularKit\/documentation\/SpooktacularKit\/RemoteDesktop","doc:\/\/SpooktacularKit\/documentation\/SpooktacularKit\/EC2MacDeployment","doc:\/\/SpooktacularKit\/documentation\/SpooktacularKit\/GitHubActionsGuide","doc:\/\/SpooktacularKit\/documentation\/SpooktacularKit\/VirtualMachineState"],["doc:\/\/SpooktacularKit\/documentation\/SpooktacularKit","doc:\/\/SpooktacularKit\/documentation\/SpooktacularKit\/RemoteDesktop","doc:\/\/SpooktacularKit\/documentation\/SpooktacularKit\/GettingStarted","doc:\/\/SpooktacularKit\/documentation\/SpooktacularKit\/EC2MacDeployment","doc:\/\/SpooktacularKit\/documentation\/SpooktacularKit\/VirtualMachineState"],["doc:\/\/SpooktacularKit\/documentation\/SpooktacularKit","doc:\/\/SpooktacularKit\/documentation\/SpooktacularKit\/RemoteDesktop","doc:\/\/SpooktacularKit\/documentation\/SpooktacularKit\/GettingStarted","doc:\/\/SpooktacularKit\/documentation\/SpooktacularKit\/GitHubActionsGuide","doc:\/\/SpooktacularKit\/documentation\/SpooktacularKit\/VirtualMachineState"],["doc:\/\/SpooktacularKit\/documentation\/SpooktacularKit","doc:\/\/SpooktacularKit\/documentation\/SpooktacularKit\/RemoteDesktop","doc:\/\/SpooktacularKit\/documentation\/SpooktacularKit\/KubernetesGuide","doc:\/\/SpooktacularKit\/documentation\/SpooktacularKit\/GitHubActionsGuide","doc:\/\/SpooktacularKit\/documentation\/SpooktacularKit\/VirtualMachineState"],["doc:\/\/SpooktacularKit\/documentation\/SpooktacularKit","doc:\/\/SpooktacularKit\/documentation\/SpooktacularKit\/Versioning","doc:\/\/SpooktacularKit\/documentation\/SpooktacularKit\/EC2MacDeployment","doc:\/\/SpooktacularKit\/documentation\/SpooktacularKit\/GitHubActionsGuide","doc:\/\/SpooktacularKit\/documentation\/SpooktacularKit\/VirtualMachineState"],["doc:\/\/SpooktacularKit\/documentation\/SpooktacularKit","doc:\/\/SpooktacularKit\/documentation\/SpooktacularKit\/Versioning","doc:\/\/SpooktacularKit\/documentation\/SpooktacularKit\/GettingStarted","doc:\/\/SpooktacularKit\/documentation\/SpooktacularKit\/EC2MacDeployment","doc:\/\/SpooktacularKit\/documentation\/SpooktacularKit\/VirtualMachineState"],["doc:\/\/SpooktacularKit\/documentation\/SpooktacularKit","doc:\/\/SpooktacularKit\/documentation\/SpooktacularKit\/Versioning","doc:\/\/SpooktacularKit\/documentation\/SpooktacularKit\/GettingStarted","doc:\/\/SpooktacularKit\/documentation\/SpooktacularKit\/GitHubActionsGuide","doc:\/\/SpooktacularKit\/documentation\/SpooktacularKit\/VirtualMachineState"],["doc:\/\/SpooktacularKit\/documentation\/SpooktacularKit","doc:\/\/SpooktacularKit\/documentation\/SpooktacularKit\/BlueBubblesGuide","doc:\/\/SpooktacularKit\/documentation\/SpooktacularKit\/GettingStarted","doc:\/\/SpooktacularKit\/documentation\/SpooktacularKit\/CLIReference","doc:\/\/SpooktacularKit\/documentation\/SpooktacularKit\/EC2MacDeployment","doc:\/\/SpooktacularKit\/documentation\/SpooktacularKit\/VirtualMachineState"],["doc:\/\/SpooktacularKit\/documentation\/SpooktacularKit","doc:\/\/SpooktacularKit\/documentation\/SpooktacularKit\/BlueBubblesGuide","doc:\/\/SpooktacularKit\/documentation\/SpooktacularKit\/GettingStarted","doc:\/\/SpooktacularKit\/documentation\/SpooktacularKit\/CLIReference","doc:\/\/SpooktacularKit\/documentation\/SpooktacularKit\/GitHubActionsGuide","doc:\/\/SpooktacularKit\/documentation\/SpooktacularKit\/VirtualMachineState"],["doc:\/\/SpooktacularKit\/documentation\/SpooktacularKit","doc:\/\/SpooktacularKit\/documentation\/SpooktacularKit\/BlueBubblesGuide","doc:\/\/SpooktacularKit\/documentation\/SpooktacularKit\/GettingStarted","doc:\/\/SpooktacularKit\/documentation\/SpooktacularKit\/EC2MacDeployment","doc:\/\/SpooktacularKit\/documentation\/SpooktacularKit\/GitHubActionsGuide","doc:\/\/SpooktacularKit\/documentation\/SpooktacularKit\/VirtualMachineState"],["doc:\/\/SpooktacularKit\/documentation\/SpooktacularKit","doc:\/\/SpooktacularKit\/documentation\/SpooktacularKit\/BlueBubblesGuide","doc:\/\/SpooktacularKit\/documentation\/SpooktacularKit\/GettingStarted","doc:\/\/SpooktacularKit\/documentation\/SpooktacularKit\/KubernetesGuide","doc:\/\/SpooktacularKit\/documentation\/SpooktacularKit\/GitHubActionsGuide","doc:\/\/SpooktacularKit\/documentation\/SpooktacularKit\/VirtualMachineState"],["doc:\/\/SpooktacularKit\/documentation\/SpooktacularKit","doc:\/\/SpooktacularKit\/documentation\/SpooktacularKit\/BlueBubblesGuide","doc:\/\/SpooktacularKit\/documentation\/SpooktacularKit\/RemoteDesktop","doc:\/\/SpooktacularKit\/documentation\/SpooktacularKit\/CLIReference","doc:\/\/SpooktacularKit\/documentation\/SpooktacularKit\/EC2MacDeployment","doc:\/\/SpooktacularKit\/documentation\/SpooktacularKit\/VirtualMachineState"],["doc:\/\/SpooktacularKit\/documentation\/SpooktacularKit","doc:\/\/SpooktacularKit\/documentation\/SpooktacularKit\/BlueBubblesGuide","doc:\/\/SpooktacularKit\/documentation\/SpooktacularKit\/RemoteDesktop","doc:\/\/SpooktacularKit\/documentation\/SpooktacularKit\/CLIReference","doc:\/\/SpooktacularKit\/documentation\/SpooktacularKit\/GitHubActionsGuide","doc:\/\/SpooktacularKit\/documentation\/SpooktacularKit\/VirtualMachineState"],["doc:\/\/SpooktacularKit\/documentation\/SpooktacularKit","doc:\/\/SpooktacularKit\/documentation\/SpooktacularKit\/BlueBubblesGuide","doc:\/\/SpooktacularKit\/documentation\/SpooktacularKit\/RemoteDesktop","doc:\/\/SpooktacularKit\/documentation\/SpooktacularKit\/EC2MacDeployment","doc:\/\/SpooktacularKit\/documentation\/SpooktacularKit\/GitHubActionsGuide","doc:\/\/SpooktacularKit\/documentation\/SpooktacularKit\/VirtualMachineState"],["doc:\/\/SpooktacularKit\/documentation\/SpooktacularKit","doc:\/\/SpooktacularKit\/documentation\/SpooktacularKit\/BlueBubblesGuide","doc:\/\/SpooktacularKit\/documentation\/SpooktacularKit\/RemoteDesktop","doc:\/\/SpooktacularKit\/documentation\/SpooktacularKit\/GettingStarted","doc:\/\/SpooktacularKit\/documentation\/SpooktacularKit\/EC2MacDeployment","doc:\/\/SpooktacularKit\/documentation\/SpooktacularKit\/VirtualMachineState"],["doc:\/\/SpooktacularKit\/documentation\/SpooktacularKit","doc:\/\/SpooktacularKit\/documentation\/SpooktacularKit\/BlueBubblesGuide","doc:\/\/SpooktacularKit\/documentation\/SpooktacularKit\/RemoteDesktop","doc:\/\/SpooktacularKit\/documentation\/SpooktacularKit\/GettingStarted","doc:\/\/SpooktacularKit\/documentation\/SpooktacularKit\/GitHubActionsGuide","doc:\/\/SpooktacularKit\/documentation\/SpooktacularKit\/VirtualMachineState"],["doc:\/\/SpooktacularKit\/documentation\/SpooktacularKit","doc:\/\/SpooktacularKit\/documentation\/SpooktacularKit\/BlueBubblesGuide","doc:\/\/SpooktacularKit\/documentation\/SpooktacularKit\/RemoteDesktop","doc:\/\/SpooktacularKit\/documentation\/SpooktacularKit\/KubernetesGuide","doc:\/\/SpooktacularKit\/documentation\/SpooktacularKit\/GitHubActionsGuide","doc:\/\/SpooktacularKit\/documentation\/SpooktacularKit\/VirtualMachineState"],["doc:\/\/SpooktacularKit\/documentation\/SpooktacularKit","doc:\/\/SpooktacularKit\/documentation\/SpooktacularKit\/CLIReference","doc:\/\/SpooktacularKit\/documentation\/SpooktacularKit\/EC2MacDeployment","doc:\/\/SpooktacularKit\/documentation\/SpooktacularKit\/KubernetesGuide","doc:\/\/SpooktacularKit\/documentation\/SpooktacularKit\/GitHubActionsGuide","doc:\/\/SpooktacularKit\/documentation\/SpooktacularKit\/VirtualMachineState"],["doc:\/\/SpooktacularKit\/documentation\/SpooktacularKit","doc:\/\/SpooktacularKit\/documentation\/SpooktacularKit\/GettingStarted","doc:\/\/SpooktacularKit\/documentation\/SpooktacularKit\/CLIReference","doc:\/\/SpooktacularKit\/documentation\/SpooktacularKit\/EC2MacDeployment","doc:\/\/SpooktacularKit\/documentation\/SpooktacularKit\/GitHubActionsGuide","doc:\/\/SpooktacularKit\/documentation\/SpooktacularKit\/VirtualMachineState"],["doc:\/\/SpooktacularKit\/documentation\/SpooktacularKit","doc:\/\/SpooktacularKit\/documentation\/SpooktacularKit\/GettingStarted","doc:\/\/SpooktacularKit\/documentation\/SpooktacularKit\/EC2MacDeployment","doc:\/\/SpooktacularKit\/documentation\/SpooktacularKit\/KubernetesGuide","doc:\/\/SpooktacularKit\/documentation\/SpooktacularKit\/GitHubActionsGuide","doc:\/\/SpooktacularKit\/documentation\/SpooktacularKit\/VirtualMachineState"],["doc:\/\/SpooktacularKit\/documentation\/SpooktacularKit","doc:\/\/SpooktacularKit\/documentation\/SpooktacularKit\/MLWorkloads","doc:\/\/SpooktacularKit\/documentation\/SpooktacularKit\/GettingStarted","doc:\/\/SpooktacularKit\/documentation\/SpooktacularKit\/CLIReference","doc:\/\/SpooktacularKit\/documentation\/SpooktacularKit\/EC2MacDeployment","doc:\/\/SpooktacularKit\/documentation\/SpooktacularKit\/VirtualMachineState"],["doc:\/\/SpooktacularKit\/documentation\/SpooktacularKit","doc:\/\/SpooktacularKit\/documentation\/SpooktacularKit\/MLWorkloads","doc:\/\/SpooktacularKit\/documentation\/SpooktacularKit\/GettingStarted","doc:\/\/SpooktacularKit\/documentation\/SpooktacularKit\/CLIReference","doc:\/\/SpooktacularKit\/documentation\/SpooktacularKit\/GitHubActionsGuide","doc:\/\/SpooktacularKit\/documentation\/SpooktacularKit\/VirtualMachineState"],["doc:\/\/SpooktacularKit\/documentation\/SpooktacularKit","doc:\/\/SpooktacularKit\/documentation\/SpooktacularKit\/MLWorkloads","doc:\/\/SpooktacularKit\/documentation\/SpooktacularKit\/GettingStarted","doc:\/\/SpooktacularKit\/documentation\/SpooktacularKit\/EC2MacDeployment","doc:\/\/SpooktacularKit\/documentation\/SpooktacularKit\/GitHubActionsGuide","doc:\/\/SpooktacularKit\/documentation\/SpooktacularKit\/VirtualMachineState"],["doc:\/\/SpooktacularKit\/documentation\/SpooktacularKit","doc:\/\/SpooktacularKit\/documentation\/SpooktacularKit\/MLWorkloads","doc:\/\/SpooktacularKit\/documentation\/SpooktacularKit\/GettingStarted","doc:\/\/SpooktacularKit\/documentation\/SpooktacularKit\/KubernetesGuide","doc:\/\/SpooktacularKit\/documentation\/SpooktacularKit\/GitHubActionsGuide","doc:\/\/SpooktacularKit\/documentation\/SpooktacularKit\/VirtualMachineState"],["doc:\/\/SpooktacularKit\/documentation\/SpooktacularKit","doc:\/\/SpooktacularKit\/documentation\/SpooktacularKit\/MLWorkloads","doc:\/\/SpooktacularKit\/documentation\/SpooktacularKit\/RemoteDesktop","doc:\/\/SpooktacularKit\/documentation\/SpooktacularKit\/CLIReference","doc:\/\/SpooktacularKit\/documentation\/SpooktacularKit\/EC2MacDeployment","doc:\/\/SpooktacularKit\/documentation\/SpooktacularKit\/VirtualMachineState"],["doc:\/\/SpooktacularKit\/documentation\/SpooktacularKit","doc:\/\/SpooktacularKit\/documentation\/SpooktacularKit\/MLWorkloads","doc:\/\/SpooktacularKit\/documentation\/SpooktacularKit\/RemoteDesktop","doc:\/\/SpooktacularKit\/documentation\/SpooktacularKit\/CLIReference","doc:\/\/SpooktacularKit\/documentation\/SpooktacularKit\/GitHubActionsGuide","doc:\/\/SpooktacularKit\/documentation\/SpooktacularKit\/VirtualMachineState"],["doc:\/\/SpooktacularKit\/documentation\/SpooktacularKit","doc:\/\/SpooktacularKit\/documentation\/SpooktacularKit\/MLWorkloads","doc:\/\/SpooktacularKit\/documentation\/SpooktacularKit\/RemoteDesktop","doc:\/\/SpooktacularKit\/documentation\/SpooktacularKit\/EC2MacDeployment","doc:\/\/SpooktacularKit\/documentation\/SpooktacularKit\/GitHubActionsGuide","doc:\/\/SpooktacularKit\/documentation\/SpooktacularKit\/VirtualMachineState"],["doc:\/\/SpooktacularKit\/documentation\/SpooktacularKit","doc:\/\/SpooktacularKit\/documentation\/SpooktacularKit\/MLWorkloads","doc:\/\/SpooktacularKit\/documentation\/SpooktacularKit\/RemoteDesktop","doc:\/\/SpooktacularKit\/documentation\/SpooktacularKit\/GettingStarted","doc:\/\/SpooktacularKit\/documentation\/SpooktacularKit\/EC2MacDeployment","doc:\/\/SpooktacularKit\/documentation\/SpooktacularKit\/VirtualMachineState"],["doc:\/\/SpooktacularKit\/documentation\/SpooktacularKit","doc:\/\/SpooktacularKit\/documentation\/SpooktacularKit\/MLWorkloads","doc:\/\/SpooktacularKit\/documentation\/SpooktacularKit\/RemoteDesktop","doc:\/\/SpooktacularKit\/documentation\/SpooktacularKit\/GettingStarted","doc:\/\/SpooktacularKit\/documentation\/SpooktacularKit\/GitHubActionsGuide","doc:\/\/SpooktacularKit\/documentation\/SpooktacularKit\/VirtualMachineState"],["doc:\/\/SpooktacularKit\/documentation\/SpooktacularKit","doc:\/\/SpooktacularKit\/documentation\/SpooktacularKit\/MLWorkloads","doc:\/\/SpooktacularKit\/documentation\/SpooktacularKit\/RemoteDesktop","doc:\/\/SpooktacularKit\/documentation\/SpooktacularKit\/KubernetesGuide","doc:\/\/SpooktacularKit\/documentation\/SpooktacularKit\/GitHubActionsGuide","doc:\/\/SpooktacularKit\/documentation\/SpooktacularKit\/VirtualMachineState"],["doc:\/\/SpooktacularKit\/documentation\/SpooktacularKit","doc:\/\/SpooktacularKit\/documentation\/SpooktacularKit\/RemoteDesktop","doc:\/\/SpooktacularKit\/documentation\/SpooktacularKit\/CLIReference","doc:\/\/SpooktacularKit\/documentation\/SpooktacularKit\/EC2MacDeployment","doc:\/\/SpooktacularKit\/documentation\/SpooktacularKit\/GitHubActionsGuide","doc:\/\/SpooktacularKit\/documentation\/SpooktacularKit\/VirtualMachineState"],["doc:\/\/SpooktacularKit\/documentation\/SpooktacularKit","doc:\/\/SpooktacularKit\/documentation\/SpooktacularKit\/RemoteDesktop","doc:\/\/SpooktacularKit\/documentation\/SpooktacularKit\/EC2MacDeployment","doc:\/\/SpooktacularKit\/documentation\/SpooktacularKit\/KubernetesGuide","doc:\/\/SpooktacularKit\/documentation\/SpooktacularKit\/GitHubActionsGuide","doc:\/\/SpooktacularKit\/documentation\/SpooktacularKit\/VirtualMachineState"],["doc:\/\/SpooktacularKit\/documentation\/SpooktacularKit","doc:\/\/SpooktacularKit\/documentation\/SpooktacularKit\/RemoteDesktop","doc:\/\/SpooktacularKit\/documentation\/SpooktacularKit\/GettingStarted","doc:\/\/SpooktacularKit\/documentation\/SpooktacularKit\/CLIReference","doc:\/\/SpooktacularKit\/documentation\/SpooktacularKit\/EC2MacDeployment","doc:\/\/SpooktacularKit\/documentation\/SpooktacularKit\/VirtualMachineState"],["doc:\/\/SpooktacularKit\/documentation\/SpooktacularKit","doc:\/\/SpooktacularKit\/documentation\/SpooktacularKit\/RemoteDesktop","doc:\/\/SpooktacularKit\/documentation\/SpooktacularKit\/GettingStarted","doc:\/\/SpooktacularKit\/documentation\/SpooktacularKit\/CLIReference","doc:\/\/SpooktacularKit\/documentation\/SpooktacularKit\/GitHubActionsGuide","doc:\/\/SpooktacularKit\/documentation\/SpooktacularKit\/VirtualMachineState"],["doc:\/\/SpooktacularKit\/documentation\/SpooktacularKit","doc:\/\/SpooktacularKit\/documentation\/SpooktacularKit\/RemoteDesktop","doc:\/\/SpooktacularKit\/documentation\/SpooktacularKit\/GettingStarted","doc:\/\/SpooktacularKit\/documentation\/SpooktacularKit\/EC2MacDeployment","doc:\/\/SpooktacularKit\/documentation\/SpooktacularKit\/GitHubActionsGuide","doc:\/\/SpooktacularKit\/documentation\/SpooktacularKit\/VirtualMachineState"],["doc:\/\/SpooktacularKit\/documentation\/SpooktacularKit","doc:\/\/SpooktacularKit\/documentation\/SpooktacularKit\/RemoteDesktop","doc:\/\/SpooktacularKit\/documentation\/SpooktacularKit\/GettingStarted","doc:\/\/SpooktacularKit\/documentation\/SpooktacularKit\/KubernetesGuide","doc:\/\/SpooktacularKit\/documentation\/SpooktacularKit\/GitHubActionsGuide","doc:\/\/SpooktacularKit\/documentation\/SpooktacularKit\/VirtualMachineState"],["doc:\/\/SpooktacularKit\/documentation\/SpooktacularKit","doc:\/\/SpooktacularKit\/documentation\/SpooktacularKit\/Versioning","doc:\/\/SpooktacularKit\/documentation\/SpooktacularKit\/EC2MacDeployment","doc:\/\/SpooktacularKit\/documentation\/SpooktacularKit\/KubernetesGuide","doc:\/\/SpooktacularKit\/documentation\/SpooktacularKit\/GitHubActionsGuide","doc:\/\/SpooktacularKit\/documentation\/SpooktacularKit\/VirtualMachineState"],["doc:\/\/SpooktacularKit\/documentation\/SpooktacularKit","doc:\/\/SpooktacularKit\/documentation\/SpooktacularKit\/Versioning","doc:\/\/SpooktacularKit\/documentation\/SpooktacularKit\/GettingStarted","doc:\/\/SpooktacularKit\/documentation\/SpooktacularKit\/CLIReference","doc:\/\/SpooktacularKit\/documentation\/SpooktacularKit\/EC2MacDeployment","doc:\/\/SpooktacularKit\/documentation\/SpooktacularKit\/VirtualMachineState"],["doc:\/\/SpooktacularKit\/documentation\/SpooktacularKit","doc:\/\/SpooktacularKit\/documentation\/SpooktacularKit\/Versioning","doc:\/\/SpooktacularKit\/documentation\/SpooktacularKit\/GettingStarted","doc:\/\/SpooktacularKit\/documentation\/SpooktacularKit\/CLIReference","doc:\/\/SpooktacularKit\/documentation\/SpooktacularKit\/GitHubActionsGuide","doc:\/\/SpooktacularKit\/documentation\/SpooktacularKit\/VirtualMachineState"],["doc:\/\/SpooktacularKit\/documentation\/SpooktacularKit","doc:\/\/SpooktacularKit\/documentation\/SpooktacularKit\/Versioning","doc:\/\/SpooktacularKit\/documentation\/SpooktacularKit\/GettingStarted","doc:\/\/SpooktacularKit\/documentation\/SpooktacularKit\/EC2MacDeployment","doc:\/\/SpooktacularKit\/documentation\/SpooktacularKit\/GitHubActionsGuide","doc:\/\/SpooktacularKit\/documentation\/SpooktacularKit\/VirtualMachineState"],["doc:\/\/SpooktacularKit\/documentation\/SpooktacularKit","doc:\/\/SpooktacularKit\/documentation\/SpooktacularKit\/Versioning","doc:\/\/SpooktacularKit\/documentation\/SpooktacularKit\/GettingStarted","doc:\/\/SpooktacularKit\/documentation\/SpooktacularKit\/KubernetesGuide","doc:\/\/SpooktacularKit\/documentation\/SpooktacularKit\/GitHubActionsGuide","doc:\/\/SpooktacularKit\/documentation\/SpooktacularKit\/VirtualMachineState"],["doc:\/\/SpooktacularKit\/documentation\/SpooktacularKit","doc:\/\/SpooktacularKit\/documentation\/SpooktacularKit\/BlueBubblesGuide","doc:\/\/SpooktacularKit\/documentation\/SpooktacularKit\/GettingStarted","doc:\/\/SpooktacularKit\/documentation\/SpooktacularKit\/CLIReference","doc:\/\/SpooktacularKit\/documentation\/SpooktacularKit\/EC2MacDeployment","doc:\/\/SpooktacularKit\/documentation\/SpooktacularKit\/GitHubActionsGuide","doc:\/\/SpooktacularKit\/documentation\/SpooktacularKit\/VirtualMachineState"],["doc:\/\/SpooktacularKit\/documentation\/SpooktacularKit","doc:\/\/SpooktacularKit\/documentation\/SpooktacularKit\/BlueBubblesGuide","doc:\/\/SpooktacularKit\/documentation\/SpooktacularKit\/GettingStarted","doc:\/\/SpooktacularKit\/documentation\/SpooktacularKit\/EC2MacDeployment","doc:\/\/SpooktacularKit\/documentation\/SpooktacularKit\/KubernetesGuide","doc:\/\/SpooktacularKit\/documentation\/SpooktacularKit\/GitHubActionsGuide","doc:\/\/SpooktacularKit\/documentation\/SpooktacularKit\/VirtualMachineState"],["doc:\/\/SpooktacularKit\/documentation\/SpooktacularKit","doc:\/\/SpooktacularKit\/documentation\/SpooktacularKit\/BlueBubblesGuide","doc:\/\/SpooktacularKit\/documentation\/SpooktacularKit\/RemoteDesktop","doc:\/\/SpooktacularKit\/documentation\/SpooktacularKit\/CLIReference","doc:\/\/SpooktacularKit\/documentation\/SpooktacularKit\/EC2MacDeployment","doc:\/\/SpooktacularKit\/documentation\/SpooktacularKit\/GitHubActionsGuide","doc:\/\/SpooktacularKit\/documentation\/SpooktacularKit\/VirtualMachineState"],["doc:\/\/SpooktacularKit\/documentation\/SpooktacularKit","doc:\/\/SpooktacularKit\/documentation\/SpooktacularKit\/BlueBubblesGuide","doc:\/\/SpooktacularKit\/documentation\/SpooktacularKit\/RemoteDesktop","doc:\/\/SpooktacularKit\/documentation\/SpooktacularKit\/EC2MacDeployment","doc:\/\/SpooktacularKit\/documentation\/SpooktacularKit\/KubernetesGuide","doc:\/\/SpooktacularKit\/documentation\/SpooktacularKit\/GitHubActionsGuide","doc:\/\/SpooktacularKit\/documentation\/SpooktacularKit\/VirtualMachineState"],["doc:\/\/SpooktacularKit\/documentation\/SpooktacularKit","doc:\/\/SpooktacularKit\/documentation\/SpooktacularKit\/BlueBubblesGuide","doc:\/\/SpooktacularKit\/documentation\/SpooktacularKit\/RemoteDesktop","doc:\/\/SpooktacularKit\/documentation\/SpooktacularKit\/GettingStarted","doc:\/\/SpooktacularKit\/documentation\/SpooktacularKit\/CLIReference","doc:\/\/SpooktacularKit\/documentation\/SpooktacularKit\/EC2MacDeployment","doc:\/\/SpooktacularKit\/documentation\/SpooktacularKit\/VirtualMachineState"],["doc:\/\/SpooktacularKit\/documentation\/SpooktacularKit","doc:\/\/SpooktacularKit\/documentation\/SpooktacularKit\/BlueBubblesGuide","doc:\/\/SpooktacularKit\/documentation\/SpooktacularKit\/RemoteDesktop","doc:\/\/SpooktacularKit\/documentation\/SpooktacularKit\/GettingStarted","doc:\/\/SpooktacularKit\/documentation\/SpooktacularKit\/CLIReference","doc:\/\/SpooktacularKit\/documentation\/SpooktacularKit\/GitHubActionsGuide","doc:\/\/SpooktacularKit\/documentation\/SpooktacularKit\/VirtualMachineState"],["doc:\/\/SpooktacularKit\/documentation\/SpooktacularKit","doc:\/\/SpooktacularKit\/documentation\/SpooktacularKit\/BlueBubblesGuide","doc:\/\/SpooktacularKit\/documentation\/SpooktacularKit\/RemoteDesktop","doc:\/\/SpooktacularKit\/documentation\/SpooktacularKit\/GettingStarted","doc:\/\/SpooktacularKit\/documentation\/SpooktacularKit\/EC2MacDeployment","doc:\/\/SpooktacularKit\/documentation\/SpooktacularKit\/GitHubActionsGuide","doc:\/\/SpooktacularKit\/documentation\/SpooktacularKit\/VirtualMachineState"],["doc:\/\/SpooktacularKit\/documentation\/SpooktacularKit","doc:\/\/SpooktacularKit\/documentation\/SpooktacularKit\/BlueBubblesGuide","doc:\/\/SpooktacularKit\/documentation\/SpooktacularKit\/RemoteDesktop","doc:\/\/SpooktacularKit\/documentation\/SpooktacularKit\/GettingStarted","doc:\/\/SpooktacularKit\/documentation\/SpooktacularKit\/KubernetesGuide","doc:\/\/SpooktacularKit\/documentation\/SpooktacularKit\/GitHubActionsGuide","doc:\/\/SpooktacularKit\/documentation\/SpooktacularKit\/VirtualMachineState"],["doc:\/\/SpooktacularKit\/documentation\/SpooktacularKit","doc:\/\/SpooktacularKit\/documentation\/SpooktacularKit\/GettingStarted","doc:\/\/SpooktacularKit\/documentation\/SpooktacularKit\/CLIReference","doc:\/\/SpooktacularKit\/documentation\/SpooktacularKit\/EC2MacDeployment","doc:\/\/SpooktacularKit\/documentation\/SpooktacularKit\/KubernetesGuide","doc:\/\/SpooktacularKit\/documentation\/SpooktacularKit\/GitHubActionsGuide","doc:\/\/SpooktacularKit\/documentation\/SpooktacularKit\/VirtualMachineState"],["doc:\/\/SpooktacularKit\/documentation\/SpooktacularKit","doc:\/\/SpooktacularKit\/documentation\/SpooktacularKit\/MLWorkloads","doc:\/\/SpooktacularKit\/documentation\/SpooktacularKit\/GettingStarted","doc:\/\/SpooktacularKit\/documentation\/SpooktacularKit\/CLIReference","doc:\/\/SpooktacularKit\/documentation\/SpooktacularKit\/EC2MacDeployment","doc:\/\/SpooktacularKit\/documentation\/SpooktacularKit\/GitHubActionsGuide","doc:\/\/SpooktacularKit\/documentation\/SpooktacularKit\/VirtualMachineState"],["doc:\/\/SpooktacularKit\/documentation\/SpooktacularKit","doc:\/\/SpooktacularKit\/documentation\/SpooktacularKit\/MLWorkloads","doc:\/\/SpooktacularKit\/documentation\/SpooktacularKit\/GettingStarted","doc:\/\/SpooktacularKit\/documentation\/SpooktacularKit\/EC2MacDeployment","doc:\/\/SpooktacularKit\/documentation\/SpooktacularKit\/KubernetesGuide","doc:\/\/SpooktacularKit\/documentation\/SpooktacularKit\/GitHubActionsGuide","doc:\/\/SpooktacularKit\/documentation\/SpooktacularKit\/VirtualMachineState"],["doc:\/\/SpooktacularKit\/documentation\/SpooktacularKit","doc:\/\/SpooktacularKit\/documentation\/SpooktacularKit\/MLWorkloads","doc:\/\/SpooktacularKit\/documentation\/SpooktacularKit\/RemoteDesktop","doc:\/\/SpooktacularKit\/documentation\/SpooktacularKit\/CLIReference","doc:\/\/SpooktacularKit\/documentation\/SpooktacularKit\/EC2MacDeployment","doc:\/\/SpooktacularKit\/documentation\/SpooktacularKit\/GitHubActionsGuide","doc:\/\/SpooktacularKit\/documentation\/SpooktacularKit\/VirtualMachineState"],["doc:\/\/SpooktacularKit\/documentation\/SpooktacularKit","doc:\/\/SpooktacularKit\/documentation\/SpooktacularKit\/MLWorkloads","doc:\/\/SpooktacularKit\/documentation\/SpooktacularKit\/RemoteDesktop","doc:\/\/SpooktacularKit\/documentation\/SpooktacularKit\/EC2MacDeployment","doc:\/\/SpooktacularKit\/documentation\/SpooktacularKit\/KubernetesGuide","doc:\/\/SpooktacularKit\/documentation\/SpooktacularKit\/GitHubActionsGuide","doc:\/\/SpooktacularKit\/documentation\/SpooktacularKit\/VirtualMachineState"],["doc:\/\/SpooktacularKit\/documentation\/SpooktacularKit","doc:\/\/SpooktacularKit\/documentation\/SpooktacularKit\/MLWorkloads","doc:\/\/SpooktacularKit\/documentation\/SpooktacularKit\/RemoteDesktop","doc:\/\/SpooktacularKit\/documentation\/SpooktacularKit\/GettingStarted","doc:\/\/SpooktacularKit\/documentation\/SpooktacularKit\/CLIReference","doc:\/\/SpooktacularKit\/documentation\/SpooktacularKit\/EC2MacDeployment","doc:\/\/SpooktacularKit\/documentation\/SpooktacularKit\/VirtualMachineState"],["doc:\/\/SpooktacularKit\/documentation\/SpooktacularKit","doc:\/\/SpooktacularKit\/documentation\/SpooktacularKit\/MLWorkloads","doc:\/\/SpooktacularKit\/documentation\/SpooktacularKit\/RemoteDesktop","doc:\/\/SpooktacularKit\/documentation\/SpooktacularKit\/GettingStarted","doc:\/\/SpooktacularKit\/documentation\/SpooktacularKit\/CLIReference","doc:\/\/SpooktacularKit\/documentation\/SpooktacularKit\/GitHubActionsGuide","doc:\/\/SpooktacularKit\/documentation\/SpooktacularKit\/VirtualMachineState"],["doc:\/\/SpooktacularKit\/documentation\/SpooktacularKit","doc:\/\/SpooktacularKit\/documentation\/SpooktacularKit\/MLWorkloads","doc:\/\/SpooktacularKit\/documentation\/SpooktacularKit\/RemoteDesktop","doc:\/\/SpooktacularKit\/documentation\/SpooktacularKit\/GettingStarted","doc:\/\/SpooktacularKit\/documentation\/SpooktacularKit\/EC2MacDeployment","doc:\/\/SpooktacularKit\/documentation\/SpooktacularKit\/GitHubActionsGuide","doc:\/\/SpooktacularKit\/documentation\/SpooktacularKit\/VirtualMachineState"],["doc:\/\/SpooktacularKit\/documentation\/SpooktacularKit","doc:\/\/SpooktacularKit\/documentation\/SpooktacularKit\/MLWorkloads","doc:\/\/SpooktacularKit\/documentation\/SpooktacularKit\/RemoteDesktop","doc:\/\/SpooktacularKit\/documentation\/SpooktacularKit\/GettingStarted","doc:\/\/SpooktacularKit\/documentation\/SpooktacularKit\/KubernetesGuide","doc:\/\/SpooktacularKit\/documentation\/SpooktacularKit\/GitHubActionsGuide","doc:\/\/SpooktacularKit\/documentation\/SpooktacularKit\/VirtualMachineState"],["doc:\/\/SpooktacularKit\/documentation\/SpooktacularKit","doc:\/\/SpooktacularKit\/documentation\/SpooktacularKit\/RemoteDesktop","doc:\/\/SpooktacularKit\/documentation\/SpooktacularKit\/CLIReference","doc:\/\/SpooktacularKit\/documentation\/SpooktacularKit\/EC2MacDeployment","doc:\/\/SpooktacularKit\/documentation\/SpooktacularKit\/KubernetesGuide","doc:\/\/SpooktacularKit\/documentation\/SpooktacularKit\/GitHubActionsGuide","doc:\/\/SpooktacularKit\/documentation\/SpooktacularKit\/VirtualMachineState"],["doc:\/\/SpooktacularKit\/documentation\/SpooktacularKit","doc:\/\/SpooktacularKit\/documentation\/SpooktacularKit\/RemoteDesktop","doc:\/\/SpooktacularKit\/documentation\/SpooktacularKit\/GettingStarted","doc:\/\/SpooktacularKit\/documentation\/SpooktacularKit\/CLIReference","doc:\/\/SpooktacularKit\/documentation\/SpooktacularKit\/EC2MacDeployment","doc:\/\/SpooktacularKit\/documentation\/SpooktacularKit\/GitHubActionsGuide","doc:\/\/SpooktacularKit\/documentation\/SpooktacularKit\/VirtualMachineState"],["doc:\/\/SpooktacularKit\/documentation\/SpooktacularKit","doc:\/\/SpooktacularKit\/documentation\/SpooktacularKit\/RemoteDesktop","doc:\/\/SpooktacularKit\/documentation\/SpooktacularKit\/GettingStarted","doc:\/\/SpooktacularKit\/documentation\/SpooktacularKit\/EC2MacDeployment","doc:\/\/SpooktacularKit\/documentation\/SpooktacularKit\/KubernetesGuide","doc:\/\/SpooktacularKit\/documentation\/SpooktacularKit\/GitHubActionsGuide","doc:\/\/SpooktacularKit\/documentation\/SpooktacularKit\/VirtualMachineState"],["doc:\/\/SpooktacularKit\/documentation\/SpooktacularKit","doc:\/\/SpooktacularKit\/documentation\/SpooktacularKit\/Versioning","doc:\/\/SpooktacularKit\/documentation\/SpooktacularKit\/GettingStarted","doc:\/\/SpooktacularKit\/documentation\/SpooktacularKit\/CLIReference","doc:\/\/SpooktacularKit\/documentation\/SpooktacularKit\/EC2MacDeployment","doc:\/\/SpooktacularKit\/documentation\/SpooktacularKit\/GitHubActionsGuide","doc:\/\/SpooktacularKit\/documentation\/SpooktacularKit\/VirtualMachineState"],["doc:\/\/SpooktacularKit\/documentation\/SpooktacularKit","doc:\/\/SpooktacularKit\/documentation\/SpooktacularKit\/Versioning","doc:\/\/SpooktacularKit\/documentation\/SpooktacularKit\/GettingStarted","doc:\/\/SpooktacularKit\/documentation\/SpooktacularKit\/EC2MacDeployment","doc:\/\/SpooktacularKit\/documentation\/SpooktacularKit\/KubernetesGuide","doc:\/\/SpooktacularKit\/documentation\/SpooktacularKit\/GitHubActionsGuide","doc:\/\/SpooktacularKit\/documentation\/SpooktacularKit\/VirtualMachineState"],["doc:\/\/SpooktacularKit\/documentation\/SpooktacularKit","doc:\/\/SpooktacularKit\/documentation\/SpooktacularKit\/BlueBubblesGuide","doc:\/\/SpooktacularKit\/documentation\/SpooktacularKit\/GettingStarted","doc:\/\/SpooktacularKit\/documentation\/SpooktacularKit\/CLIReference","doc:\/\/SpooktacularKit\/documentation\/SpooktacularKit\/EC2MacDeployment","doc:\/\/SpooktacularKit\/documentation\/SpooktacularKit\/KubernetesGuide","doc:\/\/SpooktacularKit\/documentation\/SpooktacularKit\/GitHubActionsGuide","doc:\/\/SpooktacularKit\/documentation\/SpooktacularKit\/VirtualMachineState"],["doc:\/\/SpooktacularKit\/documentation\/SpooktacularKit","doc:\/\/SpooktacularKit\/documentation\/SpooktacularKit\/BlueBubblesGuide","doc:\/\/SpooktacularKit\/documentation\/SpooktacularKit\/RemoteDesktop","doc:\/\/SpooktacularKit\/documentation\/SpooktacularKit\/CLIReference","doc:\/\/SpooktacularKit\/documentation\/SpooktacularKit\/EC2MacDeployment","doc:\/\/SpooktacularKit\/documentation\/SpooktacularKit\/KubernetesGuide","doc:\/\/SpooktacularKit\/documentation\/SpooktacularKit\/GitHubActionsGuide","doc:\/\/SpooktacularKit\/documentation\/SpooktacularKit\/VirtualMachineState"],["doc:\/\/SpooktacularKit\/documentation\/SpooktacularKit","doc:\/\/SpooktacularKit\/documentation\/SpooktacularKit\/BlueBubblesGuide","doc:\/\/SpooktacularKit\/documentation\/SpooktacularKit\/RemoteDesktop","doc:\/\/SpooktacularKit\/documentation\/SpooktacularKit\/GettingStarted","doc:\/\/SpooktacularKit\/documentation\/SpooktacularKit\/CLIReference","doc:\/\/SpooktacularKit\/documentation\/SpooktacularKit\/EC2MacDeployment","doc:\/\/SpooktacularKit\/documentation\/SpooktacularKit\/GitHubActionsGuide","doc:\/\/SpooktacularKit\/documentation\/SpooktacularKit\/VirtualMachineState"],["doc:\/\/SpooktacularKit\/documentation\/SpooktacularKit","doc:\/\/SpooktacularKit\/documentation\/SpooktacularKit\/BlueBubblesGuide","doc:\/\/SpooktacularKit\/documentation\/SpooktacularKit\/RemoteDesktop","doc:\/\/SpooktacularKit\/documentation\/SpooktacularKit\/GettingStarted","doc:\/\/SpooktacularKit\/documentation\/SpooktacularKit\/EC2MacDeployment","doc:\/\/SpooktacularKit\/documentation\/SpooktacularKit\/KubernetesGuide","doc:\/\/SpooktacularKit\/documentation\/SpooktacularKit\/GitHubActionsGuide","doc:\/\/SpooktacularKit\/documentation\/SpooktacularKit\/VirtualMachineState"],["doc:\/\/SpooktacularKit\/documentation\/SpooktacularKit","doc:\/\/SpooktacularKit\/documentation\/SpooktacularKit\/MLWorkloads","doc:\/\/SpooktacularKit\/documentation\/SpooktacularKit\/GettingStarted","doc:\/\/SpooktacularKit\/documentation\/SpooktacularKit\/CLIReference","doc:\/\/SpooktacularKit\/documentation\/SpooktacularKit\/EC2MacDeployment","doc:\/\/SpooktacularKit\/documentation\/SpooktacularKit\/KubernetesGuide","doc:\/\/SpooktacularKit\/documentation\/SpooktacularKit\/GitHubActionsGuide","doc:\/\/SpooktacularKit\/documentation\/SpooktacularKit\/VirtualMachineState"],["doc:\/\/SpooktacularKit\/documentation\/SpooktacularKit","doc:\/\/SpooktacularKit\/documentation\/SpooktacularKit\/MLWorkloads","doc:\/\/SpooktacularKit\/documentation\/SpooktacularKit\/RemoteDesktop","doc:\/\/SpooktacularKit\/documentation\/SpooktacularKit\/CLIReference","doc:\/\/SpooktacularKit\/documentation\/SpooktacularKit\/EC2MacDeployment","doc:\/\/SpooktacularKit\/documentation\/SpooktacularKit\/KubernetesGuide","doc:\/\/SpooktacularKit\/documentation\/SpooktacularKit\/GitHubActionsGuide","doc:\/\/SpooktacularKit\/documentation\/SpooktacularKit\/VirtualMachineState"],["doc:\/\/SpooktacularKit\/documentation\/SpooktacularKit","doc:\/\/SpooktacularKit\/documentation\/SpooktacularKit\/MLWorkloads","doc:\/\/SpooktacularKit\/documentation\/SpooktacularKit\/RemoteDesktop","doc:\/\/SpooktacularKit\/documentation\/SpooktacularKit\/GettingStarted","doc:\/\/SpooktacularKit\/documentation\/SpooktacularKit\/CLIReference","doc:\/\/SpooktacularKit\/documentation\/SpooktacularKit\/EC2MacDeployment","doc:\/\/SpooktacularKit\/documentation\/SpooktacularKit\/GitHubActionsGuide","doc:\/\/SpooktacularKit\/documentation\/SpooktacularKit\/VirtualMachineState"],["doc:\/\/SpooktacularKit\/documentation\/SpooktacularKit","doc:\/\/SpooktacularKit\/documentation\/SpooktacularKit\/MLWorkloads","doc:\/\/SpooktacularKit\/documentation\/SpooktacularKit\/RemoteDesktop","doc:\/\/SpooktacularKit\/documentation\/SpooktacularKit\/GettingStarted","doc:\/\/SpooktacularKit\/documentation\/SpooktacularKit\/EC2MacDeployment","doc:\/\/SpooktacularKit\/documentation\/SpooktacularKit\/KubernetesGuide","doc:\/\/SpooktacularKit\/documentation\/SpooktacularKit\/GitHubActionsGuide","doc:\/\/SpooktacularKit\/documentation\/SpooktacularKit\/VirtualMachineState"],["doc:\/\/SpooktacularKit\/documentation\/SpooktacularKit","doc:\/\/SpooktacularKit\/documentation\/SpooktacularKit\/RemoteDesktop","doc:\/\/SpooktacularKit\/documentation\/SpooktacularKit\/GettingStarted","doc:\/\/SpooktacularKit\/documentation\/SpooktacularKit\/CLIReference","doc:\/\/SpooktacularKit\/documentation\/SpooktacularKit\/EC2MacDeployment","doc:\/\/SpooktacularKit\/documentation\/SpooktacularKit\/KubernetesGuide","doc:\/\/SpooktacularKit\/documentation\/SpooktacularKit\/GitHubActionsGuide","doc:\/\/SpooktacularKit\/documentation\/SpooktacularKit\/VirtualMachineState"],["doc:\/\/SpooktacularKit\/documentation\/SpooktacularKit","doc:\/\/SpooktacularKit\/documentation\/SpooktacularKit\/Versioning","doc:\/\/SpooktacularKit\/documentation\/SpooktacularKit\/GettingStarted","doc:\/\/SpooktacularKit\/documentation\/SpooktacularKit\/CLIReference","doc:\/\/SpooktacularKit\/documentation\/SpooktacularKit\/EC2MacDeployment","doc:\/\/SpooktacularKit\/documentation\/SpooktacularKit\/KubernetesGuide","doc:\/\/SpooktacularKit\/documentation\/SpooktacularKit\/GitHubActionsGuide","doc:\/\/SpooktacularKit\/documentation\/SpooktacularKit\/VirtualMachineState"],["doc:\/\/SpooktacularKit\/documentation\/SpooktacularKit","doc:\/\/SpooktacularKit\/documentation\/SpooktacularKit\/BlueBubblesGuide","doc:\/\/SpooktacularKit\/documentation\/SpooktacularKit\/RemoteDesktop","doc:\/\/SpooktacularKit\/documentation\/SpooktacularKit\/GettingStarted","doc:\/\/SpooktacularKit\/documentation\/SpooktacularKit\/CLIReference","doc:\/\/SpooktacularKit\/documentation\/SpooktacularKit\/EC2MacDeployment","doc:\/\/SpooktacularKit\/documentation\/SpooktacularKit\/KubernetesGuide","doc:\/\/SpooktacularKit\/documentation\/SpooktacularKit\/GitHubActionsGuide","doc:\/\/SpooktacularKit\/documentation\/SpooktacularKit\/VirtualMachineState"],["doc:\/\/SpooktacularKit\/documentation\/SpooktacularKit","doc:\/\/SpooktacularKit\/documentation\/SpooktacularKit\/MLWorkloads","doc:\/\/SpooktacularKit\/documentation\/SpooktacularKit\/RemoteDesktop","doc:\/\/SpooktacularKit\/documentation\/SpooktacularKit\/GettingStarted","doc:\/\/SpooktacularKit\/documentation\/SpooktacularKit\/CLIReference","doc:\/\/SpooktacularKit\/documentation\/SpooktacularKit\/EC2MacDeployment","doc:\/\/SpooktacularKit\/documentation\/SpooktacularKit\/KubernetesGuide","doc:\/\/SpooktacularKit\/documentation\/SpooktacularKit\/GitHubActionsGuide","doc:\/\/SpooktacularKit\/documentation\/SpooktacularKit\/VirtualMachineState"]]},"metadata":{"title":"Equatable Implementations","roleHeading":"API Collection","modules":[{"name":"SpooktacularKit"}],"role":"collectionGroup"},"topicSections":[{"anchor":"Operators","generated":true,"identifiers":["doc:\/\/SpooktacularKit\/documentation\/SpooktacularKit\/VirtualMachineState\/!=(_:_:)"],"title":"Operators"}],"schemaVersion":{"minor":3,"major":0,"patch":0},"sections":[],"references":{"doc://SpooktacularKit/documentation/SpooktacularKit/KubernetesGuide":{"url":"\/documentation\/spooktacularkit\/kubernetesguide","role":"collectionGroup","identifier":"doc:\/\/SpooktacularKit\/documentation\/SpooktacularKit\/KubernetesGuide","abstract":[{"type":"text","text":"Manage macOS virtual machines as Kubernetes resources using the MacOSVM custom resource definition."}],"type":"topic","title":"Kubernetes Integration","kind":"article"},"doc://SpooktacularKit/documentation/SpooktacularKit/VirtualMachineState":{"kind":"symbol","abstract":[{"type":"text","text":"The lifecycle state of a virtual machine."}],"title":"VirtualMachineState","role":"symbol","fragments":[{"kind":"keyword","text":"enum"},{"kind":"text","text":" "},{"kind":"identifier","text":"VirtualMachineState"}],"navigatorTitle":[{"kind":"identifier","text":"VirtualMachineState"}],"identifier":"doc:\/\/SpooktacularKit\/documentation\/SpooktacularKit\/VirtualMachineState","type":"topic","url":"\/documentation\/spooktacularkit\/virtualmachinestate"},"doc://SpooktacularKit/documentation/SpooktacularKit/GitHubActionsGuide":{"identifier":"doc:\/\/SpooktacularKit\/documentation\/SpooktacularKit\/GitHubActionsGuide","url":"\/documentation\/spooktacularkit\/githubactionsguide","kind":"article","title":"Configuring GitHub Actions Runners","abstract":[{"text":"Run self-hosted macOS GitHub Actions runners in Spooktacular VMs with ephemeral isolation and automatic scaling.","type":"text"}],"type":"topic","role":"collectionGroup"},"doc://SpooktacularKit/documentation/SpooktacularKit":{"kind":"symbol","abstract":[{"type":"text","text":"Create and manage macOS virtual machines on Apple Silicon."}],"title":"SpooktacularKit","role":"collection","identifier":"doc:\/\/SpooktacularKit\/documentation\/SpooktacularKit","type":"topic","url":"\/documentation\/spooktacularkit"},"doc://SpooktacularKit/documentation/SpooktacularKit/RemoteDesktop":{"identifier":"doc:\/\/SpooktacularKit\/documentation\/SpooktacularKit\/RemoteDesktop","kind":"article","url":"\/documentation\/spooktacularkit\/remotedesktop","title":"Remote Desktop Access","abstract":[{"type":"text","text":"Connect to Spooktacular VMs via VNC for remote development, QA testing, and design review."}],"type":"topic","role":"collectionGroup"},"doc://SpooktacularKit/documentation/SpooktacularKit/Versioning":{"abstract":[{"type":"text","text":"Understand what version numbers mean and what to expect from each release."}],"title":"Versioning & Release Schedule","url":"\/documentation\/spooktacularkit\/versioning","role":"collectionGroup","type":"topic","kind":"article","identifier":"doc:\/\/SpooktacularKit\/documentation\/SpooktacularKit\/Versioning"},"doc://SpooktacularKit/documentation/SpooktacularKit/GettingStarted":{"url":"\/documentation\/spooktacularkit\/gettingstarted","role":"collectionGroup","identifier":"doc:\/\/SpooktacularKit\/documentation\/SpooktacularKit\/GettingStarted","abstract":[{"type":"text","text":"Create your first macOS virtual machine in minutes."}],"type":"topic","title":"Getting Started with Spooktacular","kind":"article"},"doc://SpooktacularKit/documentation/SpooktacularKit/VirtualMachineState/!=(_:_:)":{"url":"\/documentation\/spooktacularkit\/virtualmachinestate\/!=(_:_:)","role":"symbol","identifier":"doc:\/\/SpooktacularKit\/documentation\/SpooktacularKit\/VirtualMachineState\/!=(_:_:)","type":"topic","abstract":[],"title":"!=(_:_:)","fragments":[{"text":"static","kind":"keyword"},{"text":" ","kind":"text"},{"text":"func","kind":"keyword"},{"text":" ","kind":"text"},{"text":"!=","kind":"identifier"},{"text":" ","kind":"text"},{"text":"(","kind":"text"},{"text":"Self","kind":"typeIdentifier"},{"text":", ","kind":"text"},{"text":"Self","kind":"typeIdentifier"},{"text":") -> ","kind":"text"},{"text":"Bool","kind":"typeIdentifier","preciseIdentifier":"s:Sb"}],"kind":"symbol"},"doc://SpooktacularKit/documentation/SpooktacularKit/CLIReference":{"identifier":"doc:\/\/SpooktacularKit\/documentation\/SpooktacularKit\/CLIReference","kind":"article","url":"\/documentation\/spooktacularkit\/clireference","title":"Using the spook Command-Line Interface","abstract":[{"type":"text","text":"Manage macOS virtual machines from the terminal with the "},{"code":"spook","type":"codeVoice"},{"type":"text","text":" CLI."}],"type":"topic","role":"collectionGroup"},"doc://SpooktacularKit/documentation/SpooktacularKit/EC2MacDeployment":{"identifier":"doc:\/\/SpooktacularKit\/documentation\/SpooktacularKit\/EC2MacDeployment","kind":"article","url":"\/documentation\/spooktacularkit\/ec2macdeployment","title":"Deploying on EC2 Mac","abstract":[{"type":"text","text":"Run Spooktacular on AWS EC2 Mac dedicated hosts to double your macOS CI capacity."}],"type":"topic","role":"collectionGroup"},"doc://SpooktacularKit/documentation/SpooktacularKit/BlueBubblesGuide":{"identifier":"doc:\/\/SpooktacularKit\/documentation\/SpooktacularKit\/BlueBubblesGuide","kind":"article","url":"\/documentation\/spooktacularkit\/bluebubblesguide","title":"Running BlueBubbles iMessage Server","abstract":[{"type":"text","text":"Set up a BlueBubbles iMessage server in a macOS VM — a dramatically simpler alternative to VMware on Windows."}],"type":"topic","role":"collectionGroup"},"doc://SpooktacularKit/documentation/SpooktacularKit/MLWorkloads":{"url":"\/documentation\/spooktacularkit\/mlworkloads","role":"collectionGroup","identifier":"doc:\/\/SpooktacularKit\/documentation\/SpooktacularKit\/MLWorkloads","abstract":[{"type":"text","text":"Run ML training and inference on Apple Silicon GPUs inside Spooktacular virtual machines."}],"type":"topic","title":"Machine Learning Workloads","kind":"article"}}}