{"identifier":{"interfaceLanguage":"swift","url":"doc:\/\/SpooktacularKit\/documentation\/SpooktacularKit"},"primaryContentSections":[{"kind":"content","content":[{"anchor":"Overview","level":2,"type":"heading","text":"Overview"},{"type":"paragraph","inlineContent":[{"type":"text","text":"SpooktacularKit is the core library powering Spooktacular — a lightweight"},{"type":"text","text":" "},{"type":"text","text":"macOS app for running macOS virtual machines. Built directly on Apple’s"},{"type":"text","text":" "},{"isActive":true,"type":"reference","identifier":"https:\/\/developer.apple.com\/documentation\/virtualization"},{"type":"text","text":" "},{"type":"text","text":"framework, it provides a clean Swift API for VM lifecycle management,"},{"type":"text","text":" "},{"type":"text","text":"IPSW installation, instant APFS cloning, and enterprise provisioning."}]},{"type":"heading","level":3,"text":"Design Philosophy","anchor":"Design-Philosophy"},{"type":"paragraph","inlineContent":[{"type":"text","text":"SpooktacularKit follows Apple’s sample code patterns exactly:"}]},{"type":"unorderedList","items":[{"content":[{"inlineContent":[{"text":"Direct use of ","type":"text"},{"type":"codeVoice","code":"VZVirtualMachine"},{"text":" — no unnecessary abstractions","type":"text"}],"type":"paragraph"}]},{"content":[{"inlineContent":[{"text":"Value types (","type":"text"},{"type":"codeVoice","code":"VMSpec"},{"text":", ","type":"text"},{"type":"codeVoice","code":"VMMetadata"},{"text":", ","type":"text"},{"type":"codeVoice","code":"NetworkMode"},{"text":") for all configuration","type":"text"}],"type":"paragraph"}]},{"content":[{"inlineContent":[{"type":"codeVoice","code":"Sendable"},{"text":" conformance throughout for Swift 6 strict concurrency","type":"text"}],"type":"paragraph"}]},{"content":[{"inlineContent":[{"text":"Full DocC documentation on every public API","type":"text"}],"type":"paragraph"}]}]},{"type":"heading","level":3,"anchor":"Quick-Start","text":"Quick Start"},{"code":["\/\/ Create a VM bundle","let spec = VMSpec(cpuCount: 8, memorySizeInBytes: 16_000_000_000)","let bundle = try VMBundle.create(at: bundleURL, spec: spec)","","\/\/ Clone it instantly (APFS copy-on-write)","let clone = try CloneManager.clone(source: bundle, to: cloneURL)","","\/\/ Build a Virtualization framework configuration","let config = VZVirtualMachineConfiguration()","VMConfiguration.applySpec(spec, to: config)"],"type":"codeListing","syntax":"swift"}]}],"topicSections":[{"anchor":"Guides","title":"Guides","identifiers":["doc:\/\/SpooktacularKit\/documentation\/SpooktacularKit\/GettingStarted","doc:\/\/SpooktacularKit\/documentation\/SpooktacularKit\/CLIReference","doc:\/\/SpooktacularKit\/documentation\/SpooktacularKit\/GitHubActionsGuide","doc:\/\/SpooktacularKit\/documentation\/SpooktacularKit\/EC2MacDeployment","doc:\/\/SpooktacularKit\/documentation\/SpooktacularKit\/KubernetesGuide","doc:\/\/SpooktacularKit\/documentation\/SpooktacularKit\/MLWorkloads","doc:\/\/SpooktacularKit\/documentation\/SpooktacularKit\/RemoteDesktop","doc:\/\/SpooktacularKit\/documentation\/SpooktacularKit\/OpenClawGuide"]},{"anchor":"Virtual-Machine-Bundles","title":"Virtual Machine Bundles","identifiers":["doc:\/\/SpooktacularKit\/documentation\/SpooktacularKit\/VMBundle","doc:\/\/SpooktacularKit\/documentation\/SpooktacularKit\/VMSpec","doc:\/\/SpooktacularKit\/documentation\/SpooktacularKit\/VMMetadata","doc:\/\/SpooktacularKit\/documentation\/SpooktacularKit\/SharedFolder","doc:\/\/SpooktacularKit\/documentation\/SpooktacularKit\/VMBundleError"]},{"identifiers":["doc:\/\/SpooktacularKit\/documentation\/SpooktacularKit\/VirtualMachine","doc:\/\/SpooktacularKit\/documentation\/SpooktacularKit\/VMState","doc:\/\/SpooktacularKit\/documentation\/SpooktacularKit\/VMConfiguration"],"anchor":"VM-Lifecycle","title":"VM Lifecycle"},{"identifiers":["doc:\/\/SpooktacularKit\/documentation\/SpooktacularKit\/CloneManager"],"anchor":"Cloning","title":"Cloning"},{"identifiers":["doc:\/\/SpooktacularKit\/documentation\/SpooktacularKit\/SnapshotManager","doc:\/\/SpooktacularKit\/documentation\/SpooktacularKit\/SnapshotInfo","doc:\/\/SpooktacularKit\/documentation\/SpooktacularKit\/SnapshotError"],"anchor":"Snapshots","title":"Snapshots"},{"title":"IPSW Management","anchor":"IPSW-Management","identifiers":["doc:\/\/SpooktacularKit\/documentation\/SpooktacularKit\/RestoreImageManager","doc:\/\/SpooktacularKit\/documentation\/SpooktacularKit\/RestoreImageError"]},{"title":"Networking","anchor":"Networking","identifiers":["doc:\/\/SpooktacularKit\/documentation\/SpooktacularKit\/NetworkMode"]},{"title":"Provisioning","anchor":"Provisioning","identifiers":["doc:\/\/SpooktacularKit\/documentation\/SpooktacularKit\/ProvisioningMode"]},{"title":"Compatibility","anchor":"Compatibility","identifiers":["doc:\/\/SpooktacularKit\/documentation\/SpooktacularKit\/Compatibility"]},{"title":"Image Library","anchor":"Image-Library","identifiers":["doc:\/\/SpooktacularKit\/documentation\/SpooktacularKit\/ImageLibrary","doc:\/\/SpooktacularKit\/documentation\/SpooktacularKit\/VMImage","doc:\/\/SpooktacularKit\/documentation\/SpooktacularKit\/ImageSource"]},{"title":"Logging","anchor":"Logging","identifiers":["doc:\/\/SpooktacularKit\/documentation\/SpooktacularKit\/Log"]},{"title":"Accessibility","anchor":"Accessibility","identifiers":["doc:\/\/SpooktacularKit\/documentation\/SpooktacularKit\/AccessibilityID"]},{"title":"Articles","generated":true,"anchor":"Articles","identifiers":["doc:\/\/SpooktacularKit\/documentation\/SpooktacularKit\/BlueBubblesGuide"]},{"title":"Structures","generated":true,"anchor":"Structures","identifiers":["doc:\/\/SpooktacularKit\/documentation\/SpooktacularKit\/BootStep"]},{"title":"Enumerations","generated":true,"anchor":"Enumerations","identifiers":["doc:\/\/SpooktacularKit\/documentation\/SpooktacularKit\/BootAction","doc:\/\/SpooktacularKit\/documentation\/SpooktacularKit\/CapacityCheck","doc:\/\/SpooktacularKit\/documentation\/SpooktacularKit\/CapacityError","doc:\/\/SpooktacularKit\/documentation\/SpooktacularKit\/GitHubRunnerTemplate","doc:\/\/SpooktacularKit\/documentation\/SpooktacularKit\/IPResolver","doc:\/\/SpooktacularKit\/documentation\/SpooktacularKit\/KeyCode","doc:\/\/SpooktacularKit\/documentation\/SpooktacularKit\/Modifier","doc:\/\/SpooktacularKit\/documentation\/SpooktacularKit\/OpenClawTemplate","doc:\/\/SpooktacularKit\/documentation\/SpooktacularKit\/PIDFile","doc:\/\/SpooktacularKit\/documentation\/SpooktacularKit\/RemoteDesktopTemplate","doc:\/\/SpooktacularKit\/documentation\/SpooktacularKit\/SSHError","doc:\/\/SpooktacularKit\/documentation\/SpooktacularKit\/SSHExecutor","doc:\/\/SpooktacularKit\/documentation\/SpooktacularKit\/SetupAutomation"]},{"title":"Extended Modules","generated":true,"anchor":"Extended-Modules","identifiers":["doc:\/\/SpooktacularKit\/documentation\/SpooktacularKit\/Foundation"]}],"variants":[{"paths":["\/documentation\/spooktacularkit"],"traits":[{"interfaceLanguage":"swift"}]}],"metadata":{"title":"SpooktacularKit","modules":[{"name":"SpooktacularKit"}],"roleHeading":"Framework","role":"collection","symbolKind":"module","externalID":"SpooktacularKit"},"kind":"symbol","schemaVersion":{"minor":3,"major":0,"patch":0},"hierarchy":{"paths":[[]]},"abstract":[{"text":"Create and manage macOS virtual machines on Apple Silicon.","type":"text"}],"sections":[],"references":{"doc://SpooktacularKit/documentation/SpooktacularKit/OpenClawGuide":{"kind":"article","title":"Running OpenClaw in Virtual Machines","url":"\/documentation\/spooktacularkit\/openclawguide","type":"topic","abstract":[{"type":"text","text":"Run two isolated OpenClaw AI agent instances on a single Mac — each with its own workspace, channels, and API keys."}],"identifier":"doc:\/\/SpooktacularKit\/documentation\/SpooktacularKit\/OpenClawGuide","role":"collectionGroup"},"doc://SpooktacularKit/documentation/SpooktacularKit/Log":{"navigatorTitle":[{"text":"Log","kind":"identifier"}],"kind":"symbol","fragments":[{"text":"enum","kind":"keyword"},{"text":" ","kind":"text"},{"text":"Log","kind":"identifier"}],"title":"Log","url":"\/documentation\/spooktacularkit\/log","type":"topic","abstract":[{"type":"text","text":"Centralized loggers for SpooktacularKit."}],"identifier":"doc:\/\/SpooktacularKit\/documentation\/SpooktacularKit\/Log","role":"symbol"},"doc://SpooktacularKit/documentation/SpooktacularKit/RestoreImageError":{"title":"RestoreImageError","identifier":"doc:\/\/SpooktacularKit\/documentation\/SpooktacularKit\/RestoreImageError","url":"\/documentation\/spooktacularkit\/restoreimageerror","type":"topic","role":"symbol","kind":"symbol","fragments":[{"kind":"keyword","text":"enum"},{"kind":"text","text":" "},{"kind":"identifier","text":"RestoreImageError"}],"abstract":[{"text":"An error that occurs during restore image operations.","type":"text"}],"navigatorTitle":[{"kind":"identifier","text":"RestoreImageError"}]},"doc://SpooktacularKit/documentation/SpooktacularKit/GitHubRunnerTemplate":{"abstract":[{"text":"Generates user-data scripts for GitHub Actions runner VMs.","type":"text"}],"fragments":[{"kind":"keyword","text":"enum"},{"kind":"text","text":" "},{"kind":"identifier","text":"GitHubRunnerTemplate"}],"navigatorTitle":[{"kind":"identifier","text":"GitHubRunnerTemplate"}],"kind":"symbol","role":"symbol","title":"GitHubRunnerTemplate","type":"topic","identifier":"doc:\/\/SpooktacularKit\/documentation\/SpooktacularKit\/GitHubRunnerTemplate","url":"\/documentation\/spooktacularkit\/githubrunnertemplate"},"doc://SpooktacularKit/documentation/SpooktacularKit/OpenClawTemplate":{"abstract":[{"type":"text","text":"Generates user-data scripts for OpenClaw AI agent VMs."}],"type":"topic","title":"OpenClawTemplate","kind":"symbol","fragments":[{"text":"enum","kind":"keyword"},{"text":" ","kind":"text"},{"text":"OpenClawTemplate","kind":"identifier"}],"role":"symbol","identifier":"doc:\/\/SpooktacularKit\/documentation\/SpooktacularKit\/OpenClawTemplate","navigatorTitle":[{"text":"OpenClawTemplate","kind":"identifier"}],"url":"\/documentation\/spooktacularkit\/openclawtemplate"},"doc://SpooktacularKit/documentation/SpooktacularKit/SnapshotInfo":{"url":"\/documentation\/spooktacularkit\/snapshotinfo","title":"SnapshotInfo","identifier":"doc:\/\/SpooktacularKit\/documentation\/SpooktacularKit\/SnapshotInfo","type":"topic","role":"symbol","kind":"symbol","fragments":[{"kind":"keyword","text":"struct"},{"kind":"text","text":" "},{"kind":"identifier","text":"SnapshotInfo"}],"abstract":[{"type":"text","text":"Metadata about a saved VM snapshot."}],"navigatorTitle":[{"text":"SnapshotInfo","kind":"identifier"}]},"https://developer.apple.com/documentation/virtualization":{"titleInlineContent":[{"type":"text","text":"Virtualization"}],"title":"Virtualization","type":"link","url":"https:\/\/developer.apple.com\/documentation\/virtualization","identifier":"https:\/\/developer.apple.com\/documentation\/virtualization"},"doc://SpooktacularKit/documentation/SpooktacularKit/VMMetadata":{"abstract":[{"text":"Runtime metadata for a virtual machine.","type":"text"}],"fragments":[{"text":"struct","kind":"keyword"},{"text":" ","kind":"text"},{"text":"VMMetadata","kind":"identifier"}],"navigatorTitle":[{"kind":"identifier","text":"VMMetadata"}],"kind":"symbol","role":"symbol","title":"VMMetadata","type":"topic","url":"\/documentation\/spooktacularkit\/vmmetadata","identifier":"doc:\/\/SpooktacularKit\/documentation\/SpooktacularKit\/VMMetadata"},"doc://SpooktacularKit/documentation/SpooktacularKit/BootAction":{"abstract":[{"text":"A keyboard action to send to the VM during Setup Assistant automation.","type":"text"}],"type":"topic","title":"BootAction","kind":"symbol","fragments":[{"kind":"keyword","text":"enum"},{"kind":"text","text":" "},{"kind":"identifier","text":"BootAction"}],"role":"symbol","identifier":"doc:\/\/SpooktacularKit\/documentation\/SpooktacularKit\/BootAction","navigatorTitle":[{"kind":"identifier","text":"BootAction"}],"url":"\/documentation\/spooktacularkit\/bootaction"},"doc://SpooktacularKit/documentation/SpooktacularKit/SetupAutomation":{"navigatorTitle":[{"kind":"identifier","text":"SetupAutomation"}],"kind":"symbol","fragments":[{"kind":"keyword","text":"enum"},{"kind":"text","text":" "},{"text":"SetupAutomation","kind":"identifier"}],"title":"SetupAutomation","identifier":"doc:\/\/SpooktacularKit\/documentation\/SpooktacularKit\/SetupAutomation","type":"topic","url":"\/documentation\/spooktacularkit\/setupautomation","abstract":[{"type":"text","text":"Automated macOS Setup Assistant sequences for headless VM provisioning."}],"role":"symbol"},"doc://SpooktacularKit/documentation/SpooktacularKit":{"url":"\/documentation\/spooktacularkit","type":"topic","title":"SpooktacularKit","kind":"symbol","role":"collection","identifier":"doc:\/\/SpooktacularKit\/documentation\/SpooktacularKit","abstract":[{"text":"Create and manage macOS virtual machines on Apple Silicon.","type":"text"}]},"doc://SpooktacularKit/documentation/SpooktacularKit/AccessibilityID":{"abstract":[{"type":"text","text":"Shared accessibility identifiers for UI testing."}],"role":"symbol","kind":"symbol","url":"\/documentation\/spooktacularkit\/accessibilityid","fragments":[{"kind":"keyword","text":"enum"},{"kind":"text","text":" "},{"kind":"identifier","text":"AccessibilityID"}],"navigatorTitle":[{"kind":"identifier","text":"AccessibilityID"}],"identifier":"doc:\/\/SpooktacularKit\/documentation\/SpooktacularKit\/AccessibilityID","type":"topic","title":"AccessibilityID"},"doc://SpooktacularKit/documentation/SpooktacularKit/ImageSource":{"url":"\/documentation\/spooktacularkit\/imagesource","type":"topic","title":"ImageSource","kind":"symbol","fragments":[{"text":"enum","kind":"keyword"},{"text":" ","kind":"text"},{"text":"ImageSource","kind":"identifier"}],"role":"symbol","identifier":"doc:\/\/SpooktacularKit\/documentation\/SpooktacularKit\/ImageSource","navigatorTitle":[{"text":"ImageSource","kind":"identifier"}],"abstract":[{"text":"The source type for a VM image.","type":"text"}]},"doc://SpooktacularKit/documentation/SpooktacularKit/CLIReference":{"url":"\/documentation\/spooktacularkit\/clireference","kind":"article","role":"collectionGroup","abstract":[{"text":"Complete reference for the ","type":"text"},{"code":"spook","type":"codeVoice"},{"type":"text","text":" command-line interface."}],"type":"topic","identifier":"doc:\/\/SpooktacularKit\/documentation\/SpooktacularKit\/CLIReference","title":"CLI Reference"},"doc://SpooktacularKit/documentation/SpooktacularKit/ImageLibrary":{"navigatorTitle":[{"kind":"identifier","text":"ImageLibrary"}],"kind":"symbol","fragments":[{"kind":"keyword","text":"class"},{"kind":"text","text":" "},{"kind":"identifier","text":"ImageLibrary"}],"title":"ImageLibrary","identifier":"doc:\/\/SpooktacularKit\/documentation\/SpooktacularKit\/ImageLibrary","type":"topic","abstract":[{"type":"text","text":"Manages the local cache of VM images."}],"url":"\/documentation\/spooktacularkit\/imagelibrary","role":"symbol"},"doc://SpooktacularKit/documentation/SpooktacularKit/VMSpec":{"fragments":[{"kind":"keyword","text":"struct"},{"kind":"text","text":" "},{"kind":"identifier","text":"VMSpec"}],"identifier":"doc:\/\/SpooktacularKit\/documentation\/SpooktacularKit\/VMSpec","abstract":[{"text":"The hardware specification for a virtual machine.","type":"text"}],"type":"topic","url":"\/documentation\/spooktacularkit\/vmspec","role":"symbol","navigatorTitle":[{"kind":"identifier","text":"VMSpec"}],"title":"VMSpec","kind":"symbol"},"doc://SpooktacularKit/documentation/SpooktacularKit/SharedFolder":{"abstract":[{"type":"text","text":"A directory shared between the host and the virtual machine."}],"role":"symbol","kind":"symbol","url":"\/documentation\/spooktacularkit\/sharedfolder","fragments":[{"kind":"keyword","text":"struct"},{"kind":"text","text":" "},{"kind":"identifier","text":"SharedFolder"}],"navigatorTitle":[{"kind":"identifier","text":"SharedFolder"}],"identifier":"doc:\/\/SpooktacularKit\/documentation\/SpooktacularKit\/SharedFolder","type":"topic","title":"SharedFolder"},"doc://SpooktacularKit/documentation/SpooktacularKit/Compatibility":{"fragments":[{"text":"enum","kind":"keyword"},{"text":" ","kind":"text"},{"kind":"identifier","text":"Compatibility"}],"abstract":[{"type":"text","text":"Checks version compatibility between the host macOS"},{"type":"text","text":" "},{"text":"and a macOS restore image (IPSW).","type":"text"}],"identifier":"doc:\/\/SpooktacularKit\/documentation\/SpooktacularKit\/Compatibility","type":"topic","url":"\/documentation\/spooktacularkit\/compatibility","role":"symbol","navigatorTitle":[{"kind":"identifier","text":"Compatibility"}],"title":"Compatibility","kind":"symbol"},"doc://SpooktacularKit/documentation/SpooktacularKit/NetworkMode":{"abstract":[{"text":"The network configuration mode for a virtual machine.","type":"text"}],"fragments":[{"kind":"keyword","text":"enum"},{"kind":"text","text":" "},{"kind":"identifier","text":"NetworkMode"}],"navigatorTitle":[{"kind":"identifier","text":"NetworkMode"}],"kind":"symbol","role":"symbol","title":"NetworkMode","type":"topic","identifier":"doc:\/\/SpooktacularKit\/documentation\/SpooktacularKit\/NetworkMode","url":"\/documentation\/spooktacularkit\/networkmode"},"doc://SpooktacularKit/documentation/SpooktacularKit/VMState":{"abstract":[{"type":"text","text":"The lifecycle state of a virtual machine."}],"type":"topic","title":"VMState","kind":"symbol","fragments":[{"kind":"keyword","text":"enum"},{"kind":"text","text":" "},{"kind":"identifier","text":"VMState"}],"role":"symbol","identifier":"doc:\/\/SpooktacularKit\/documentation\/SpooktacularKit\/VMState","navigatorTitle":[{"kind":"identifier","text":"VMState"}],"url":"\/documentation\/spooktacularkit\/vmstate"},"doc://SpooktacularKit/documentation/SpooktacularKit/VMImage":{"abstract":[{"type":"text","text":"A cached VM image available for creating new virtual machines."}],"fragments":[{"kind":"keyword","text":"struct"},{"kind":"text","text":" "},{"kind":"identifier","text":"VMImage"}],"navigatorTitle":[{"kind":"identifier","text":"VMImage"}],"kind":"symbol","role":"symbol","title":"VMImage","type":"topic","identifier":"doc:\/\/SpooktacularKit\/documentation\/SpooktacularKit\/VMImage","url":"\/documentation\/spooktacularkit\/vmimage"},"doc://SpooktacularKit/documentation/SpooktacularKit/GitHubActionsGuide":{"kind":"article","title":"GitHub Actions Runners","identifier":"doc:\/\/SpooktacularKit\/documentation\/SpooktacularKit\/GitHubActionsGuide","type":"topic","abstract":[{"type":"text","text":"Run self-hosted macOS GitHub Actions runners in Spooktacular VMs with ephemeral isolation and automatic scaling."}],"url":"\/documentation\/spooktacularkit\/githubactionsguide","role":"collectionGroup"},"doc://SpooktacularKit/documentation/SpooktacularKit/GettingStarted":{"abstract":[{"type":"text","text":"Create your first macOS virtual machine in minutes."}],"kind":"article","role":"collectionGroup","title":"Getting Started with Spooktacular","type":"topic","identifier":"doc:\/\/SpooktacularKit\/documentation\/SpooktacularKit\/GettingStarted","url":"\/documentation\/spooktacularkit\/gettingstarted"},"doc://SpooktacularKit/documentation/SpooktacularKit/KeyCode":{"url":"\/documentation\/spooktacularkit\/keycode","type":"topic","title":"KeyCode","kind":"symbol","fragments":[{"kind":"keyword","text":"enum"},{"kind":"text","text":" "},{"text":"KeyCode","kind":"identifier"}],"role":"symbol","identifier":"doc:\/\/SpooktacularKit\/documentation\/SpooktacularKit\/KeyCode","navigatorTitle":[{"kind":"identifier","text":"KeyCode"}],"abstract":[{"text":"Virtual key codes for Setup Assistant navigation.","type":"text"}]},"doc://SpooktacularKit/documentation/SpooktacularKit/MLWorkloads":{"abstract":[{"text":"Run ML training and inference on Apple Silicon GPUs inside Spooktacular virtual machines.","type":"text"}],"type":"topic","title":"Machine Learning Workloads","kind":"article","role":"collectionGroup","identifier":"doc:\/\/SpooktacularKit\/documentation\/SpooktacularKit\/MLWorkloads","url":"\/documentation\/spooktacularkit\/mlworkloads"},"doc://SpooktacularKit/documentation/SpooktacularKit/EC2MacDeployment":{"abstract":[{"text":"Run Spooktacular on AWS EC2 Mac dedicated hosts to double your macOS CI capacity.","type":"text"}],"type":"topic","title":"Deploying on EC2 Mac","kind":"article","role":"collectionGroup","identifier":"doc:\/\/SpooktacularKit\/documentation\/SpooktacularKit\/EC2MacDeployment","url":"\/documentation\/spooktacularkit\/ec2macdeployment"},"doc://SpooktacularKit/documentation/SpooktacularKit/PIDFile":{"navigatorTitle":[{"kind":"identifier","text":"PIDFile"}],"kind":"symbol","fragments":[{"kind":"keyword","text":"enum"},{"kind":"text","text":" "},{"kind":"identifier","text":"PIDFile"}],"title":"PIDFile","url":"\/documentation\/spooktacularkit\/pidfile","type":"topic","abstract":[{"type":"text","text":"Manages PID files for tracking running virtual machines."}],"identifier":"doc:\/\/SpooktacularKit\/documentation\/SpooktacularKit\/PIDFile","role":"symbol"},"doc://SpooktacularKit/documentation/SpooktacularKit/KubernetesGuide":{"abstract":[{"type":"text","text":"Manage macOS virtual machines as Kubernetes resources with custom CRDs and an operator."}],"type":"topic","title":"Kubernetes Integration","kind":"article","role":"collectionGroup","identifier":"doc:\/\/SpooktacularKit\/documentation\/SpooktacularKit\/KubernetesGuide","url":"\/documentation\/spooktacularkit\/kubernetesguide"},"doc://SpooktacularKit/documentation/SpooktacularKit/CapacityError":{"navigatorTitle":[{"kind":"identifier","text":"CapacityError"}],"kind":"symbol","fragments":[{"kind":"keyword","text":"enum"},{"text":" ","kind":"text"},{"kind":"identifier","text":"CapacityError"}],"title":"CapacityError","type":"topic","url":"\/documentation\/spooktacularkit\/capacityerror","abstract":[{"text":"An error indicating the concurrent VM limit has been reached.","type":"text"}],"identifier":"doc:\/\/SpooktacularKit\/documentation\/SpooktacularKit\/CapacityError","role":"symbol"},"doc://SpooktacularKit/documentation/SpooktacularKit/ProvisioningMode":{"navigatorTitle":[{"kind":"identifier","text":"ProvisioningMode"}],"kind":"symbol","fragments":[{"kind":"keyword","text":"enum"},{"kind":"text","text":" "},{"kind":"identifier","text":"ProvisioningMode"}],"title":"ProvisioningMode","type":"topic","identifier":"doc:\/\/SpooktacularKit\/documentation\/SpooktacularKit\/ProvisioningMode","abstract":[{"type":"text","text":"The strategy for executing a user-data script on a VM."}],"url":"\/documentation\/spooktacularkit\/provisioningmode","role":"symbol"},"doc://SpooktacularKit/documentation/SpooktacularKit/IPResolver":{"fragments":[{"kind":"keyword","text":"enum"},{"kind":"text","text":" "},{"kind":"identifier","text":"IPResolver"}],"abstract":[{"text":"Resolves the IP address of a running VM by its MAC address.","type":"text"}],"type":"topic","identifier":"doc:\/\/SpooktacularKit\/documentation\/SpooktacularKit\/IPResolver","url":"\/documentation\/spooktacularkit\/ipresolver","role":"symbol","navigatorTitle":[{"kind":"identifier","text":"IPResolver"}],"title":"IPResolver","kind":"symbol"},"doc://SpooktacularKit/documentation/SpooktacularKit/Foundation":{"kind":"symbol","title":"Foundation","url":"\/documentation\/spooktacularkit\/foundation","type":"topic","abstract":[],"identifier":"doc:\/\/SpooktacularKit\/documentation\/SpooktacularKit\/Foundation","role":"collection"},"doc://SpooktacularKit/documentation/SpooktacularKit/RestoreImageManager":{"type":"topic","kind":"symbol","url":"\/documentation\/spooktacularkit\/restoreimagemanager","abstract":[{"text":"Manages macOS restore images (IPSWs) for virtual machine installation.","type":"text"}],"navigatorTitle":[{"kind":"identifier","text":"RestoreImageManager"}],"title":"RestoreImageManager","identifier":"doc:\/\/SpooktacularKit\/documentation\/SpooktacularKit\/RestoreImageManager","role":"symbol","fragments":[{"kind":"keyword","text":"class"},{"kind":"text","text":" "},{"kind":"identifier","text":"RestoreImageManager"}]},"doc://SpooktacularKit/documentation/SpooktacularKit/BootStep":{"url":"\/documentation\/spooktacularkit\/bootstep","kind":"symbol","navigatorTitle":[{"kind":"identifier","text":"BootStep"}],"role":"symbol","fragments":[{"kind":"keyword","text":"struct"},{"kind":"text","text":" "},{"kind":"identifier","text":"BootStep"}],"abstract":[{"text":"A single step in a Setup Assistant automation sequence.","type":"text"}],"identifier":"doc:\/\/SpooktacularKit\/documentation\/SpooktacularKit\/BootStep","type":"topic","title":"BootStep"},"doc://SpooktacularKit/documentation/SpooktacularKit/SnapshotError":{"abstract":[{"text":"An error that occurs during snapshot operations.","type":"text"}],"fragments":[{"kind":"keyword","text":"enum"},{"kind":"text","text":" "},{"kind":"identifier","text":"SnapshotError"}],"navigatorTitle":[{"kind":"identifier","text":"SnapshotError"}],"kind":"symbol","role":"symbol","title":"SnapshotError","type":"topic","url":"\/documentation\/spooktacularkit\/snapshoterror","identifier":"doc:\/\/SpooktacularKit\/documentation\/SpooktacularKit\/SnapshotError"},"doc://SpooktacularKit/documentation/SpooktacularKit/VMBundle":{"fragments":[{"text":"struct","kind":"keyword"},{"text":" ","kind":"text"},{"kind":"identifier","text":"VMBundle"}],"abstract":[{"text":"A virtual machine bundle stored on disk.","type":"text"}],"identifier":"doc:\/\/SpooktacularKit\/documentation\/SpooktacularKit\/VMBundle","type":"topic","url":"\/documentation\/spooktacularkit\/vmbundle","role":"symbol","navigatorTitle":[{"text":"VMBundle","kind":"identifier"}],"title":"VMBundle","kind":"symbol"},"doc://SpooktacularKit/documentation/SpooktacularKit/SnapshotManager":{"url":"\/documentation\/spooktacularkit\/snapshotmanager","kind":"symbol","type":"topic","abstract":[{"text":"Manages disk-level snapshots for virtual machine bundles.","type":"text"}],"navigatorTitle":[{"kind":"identifier","text":"SnapshotManager"}],"title":"SnapshotManager","identifier":"doc:\/\/SpooktacularKit\/documentation\/SpooktacularKit\/SnapshotManager","role":"symbol","fragments":[{"kind":"keyword","text":"enum"},{"kind":"text","text":" "},{"kind":"identifier","text":"SnapshotManager"}]},"doc://SpooktacularKit/documentation/SpooktacularKit/CapacityCheck":{"fragments":[{"kind":"keyword","text":"enum"},{"kind":"text","text":" "},{"kind":"identifier","text":"CapacityCheck"}],"abstract":[{"text":"Enforces the Apple Silicon concurrent VM limit.","type":"text"}],"type":"topic","identifier":"doc:\/\/SpooktacularKit\/documentation\/SpooktacularKit\/CapacityCheck","url":"\/documentation\/spooktacularkit\/capacitycheck","role":"symbol","navigatorTitle":[{"kind":"identifier","text":"CapacityCheck"}],"title":"CapacityCheck","kind":"symbol"},"doc://SpooktacularKit/documentation/SpooktacularKit/RemoteDesktop":{"kind":"article","title":"Remote Desktop Access","identifier":"doc:\/\/SpooktacularKit\/documentation\/SpooktacularKit\/RemoteDesktop","type":"topic","url":"\/documentation\/spooktacularkit\/remotedesktop","abstract":[{"type":"text","text":"Connect to Spooktacular VMs via VNC for remote development, QA testing, and design review."}],"role":"collectionGroup"},"doc://SpooktacularKit/documentation/SpooktacularKit/VMConfiguration":{"title":"VMConfiguration","identifier":"doc:\/\/SpooktacularKit\/documentation\/SpooktacularKit\/VMConfiguration","url":"\/documentation\/spooktacularkit\/vmconfiguration","type":"topic","role":"symbol","kind":"symbol","fragments":[{"kind":"keyword","text":"enum"},{"kind":"text","text":" "},{"kind":"identifier","text":"VMConfiguration"}],"abstract":[{"text":"Builds ","type":"text"},{"code":"VZVirtualMachineConfiguration","type":"codeVoice"},{"text":" objects from a ","type":"text"},{"isActive":true,"type":"reference","identifier":"doc:\/\/SpooktacularKit\/documentation\/SpooktacularKit\/VMSpec"},{"text":".","type":"text"}],"navigatorTitle":[{"kind":"identifier","text":"VMConfiguration"}]},"doc://SpooktacularKit/documentation/SpooktacularKit/VirtualMachine":{"abstract":[{"type":"text","text":"A running macOS virtual machine."}],"type":"topic","title":"VirtualMachine","kind":"symbol","fragments":[{"kind":"keyword","text":"class"},{"kind":"text","text":" "},{"kind":"identifier","text":"VirtualMachine"}],"role":"symbol","identifier":"doc:\/\/SpooktacularKit\/documentation\/SpooktacularKit\/VirtualMachine","navigatorTitle":[{"kind":"identifier","text":"VirtualMachine"}],"url":"\/documentation\/spooktacularkit\/virtualmachine"},"doc://SpooktacularKit/documentation/SpooktacularKit/Modifier":{"navigatorTitle":[{"kind":"identifier","text":"Modifier"}],"kind":"symbol","fragments":[{"kind":"keyword","text":"enum"},{"kind":"text","text":" "},{"kind":"identifier","text":"Modifier"}],"title":"Modifier","identifier":"doc:\/\/SpooktacularKit\/documentation\/SpooktacularKit\/Modifier","type":"topic","abstract":[{"text":"Modifier keys for keyboard shortcuts.","type":"text"}],"url":"\/documentation\/spooktacularkit\/modifier","role":"symbol"},"doc://SpooktacularKit/documentation/SpooktacularKit/SSHError":{"title":"SSHError","identifier":"doc:\/\/SpooktacularKit\/documentation\/SpooktacularKit\/SSHError","url":"\/documentation\/spooktacularkit\/ssherror","type":"topic","role":"symbol","kind":"symbol","fragments":[{"kind":"keyword","text":"enum"},{"kind":"text","text":" "},{"kind":"identifier","text":"SSHError"}],"abstract":[{"text":"An error that occurs during SSH operations.","type":"text"}],"navigatorTitle":[{"kind":"identifier","text":"SSHError"}]},"doc://SpooktacularKit/documentation/SpooktacularKit/BlueBubblesGuide":{"abstract":[{"text":"Set up a BlueBubbles iMessage server in a macOS VM — a dramatically simpler alternative to VMware on Windows.","type":"text"}],"kind":"article","role":"collectionGroup","title":"Running BlueBubbles iMessage Server","type":"topic","identifier":"doc:\/\/SpooktacularKit\/documentation\/SpooktacularKit\/BlueBubblesGuide","url":"\/documentation\/spooktacularkit\/bluebubblesguide"},"doc://SpooktacularKit/documentation/SpooktacularKit/SSHExecutor":{"abstract":[{"text":"Executes scripts on a VM via SSH.","type":"text"}],"type":"topic","title":"SSHExecutor","kind":"symbol","fragments":[{"kind":"keyword","text":"enum"},{"kind":"text","text":" "},{"kind":"identifier","text":"SSHExecutor"}],"role":"symbol","identifier":"doc:\/\/SpooktacularKit\/documentation\/SpooktacularKit\/SSHExecutor","navigatorTitle":[{"kind":"identifier","text":"SSHExecutor"}],"url":"\/documentation\/spooktacularkit\/sshexecutor"},"doc://SpooktacularKit/documentation/SpooktacularKit/RemoteDesktopTemplate":{"navigatorTitle":[{"text":"RemoteDesktopTemplate","kind":"identifier"}],"kind":"symbol","fragments":[{"kind":"keyword","text":"enum"},{"text":" ","kind":"text"},{"text":"RemoteDesktopTemplate","kind":"identifier"}],"title":"RemoteDesktopTemplate","url":"\/documentation\/spooktacularkit\/remotedesktoptemplate","type":"topic","abstract":[{"type":"text","text":"Generates user-data scripts for remote desktop (Screen Sharing) VMs."}],"identifier":"doc:\/\/SpooktacularKit\/documentation\/SpooktacularKit\/RemoteDesktopTemplate","role":"symbol"},"doc://SpooktacularKit/documentation/SpooktacularKit/CloneManager":{"fragments":[{"kind":"keyword","text":"enum"},{"kind":"text","text":" "},{"kind":"identifier","text":"CloneManager"}],"abstract":[{"type":"text","text":"Creates copy-on-write clones of virtual machine bundles."}],"identifier":"doc:\/\/SpooktacularKit\/documentation\/SpooktacularKit\/CloneManager","type":"topic","url":"\/documentation\/spooktacularkit\/clonemanager","role":"symbol","navigatorTitle":[{"kind":"identifier","text":"CloneManager"}],"title":"CloneManager","kind":"symbol"},"doc://SpooktacularKit/documentation/SpooktacularKit/VMBundleError":{"title":"VMBundleError","url":"\/documentation\/spooktacularkit\/vmbundleerror","identifier":"doc:\/\/SpooktacularKit\/documentation\/SpooktacularKit\/VMBundleError","type":"topic","role":"symbol","kind":"symbol","fragments":[{"text":"enum","kind":"keyword"},{"text":" ","kind":"text"},{"text":"VMBundleError","kind":"identifier"}],"abstract":[{"type":"text","text":"An error that occurs during VM bundle operations."}],"navigatorTitle":[{"text":"VMBundleError","kind":"identifier"}]}}}